[{"tags":["sexual assault","assault"],"id":724739984515842048,"text":"RT @SSU_1961: It's on all of us to stop sexual assault. #SonomaState took the pledge to be a part of the solution and you can too https://t\u2026","keywords":["SonomaState"],"urls":["http://bit.ly/1HmA1bI"],"user_verified":false,"class":"Rape","date":"2016-04-25T11:20:51Z","lang":"en","retweets":2,"city":"San Francisco"},{"tags":["sexual assault","assault"],"id":724731814590484480,"text":"Be sure to show your continued support this week for Sexual Assault Awareness Month #usfca\u2026 https://t.co/zI0bXMYhVw","keywords":["usfca"],"urls":["https://www.instagram.com/p/BEo_vHFiyoH/"],"user_verified":false,"class":"Rape","date":"2016-04-25T10:48:24Z","lang":"en","retweets":0,"city":"San Francisco"},{"tags":["sexual assault","assault"],"id":724729037617143808,"text":"Bill Cosby loses attempt to get sexual assault case thrown out https://t.co/SzCbwyN6JO","keywords":[],"urls":["http://www.huffingtonpost.com/entry/bill-cosby-loses-attempt-to-stop-sexual-assault-case_us_571e6eede4b0b49df6a898bc?go6uaphpfmyevzpvi"],"user_verified":false,"class":"Rape","date":"2016-04-25T10:37:22Z","lang":"en","retweets":0,"city":"San Francisco"},{"tags":["assault"],"id":724726468106964992,"text":"\" You shouldn\u2019t have to be both available and capable of preventing your own assault. #SAAM https://t.co/0KoLgQvqY2 https://t.co/DJhEgQpWRj","keywords":["SAAM"],"urls":["http://ow.ly/4n5oSv"],"user_verified":false,"class":"Assault","date":"2016-04-25T10:27:09Z","lang":"en","retweets":0,"city":"San Francisco"},{"tags":[],"id":724711920998084608,"text":"RT @Clayman_Inst: Congrats to student activists for being change agents! Join @Clayman_Inst https://t.co/n5BnVOLQZe https://t.co/zmtV85VxyQ","keywords":[],"urls":["http://gender.stanford.edu/news/2016/breaking-culture-sexual-assault"],"user_verified":false,"class":"Unclassified","date":"2016-04-25T09:29:21Z","lang":"en","retweets":3,"city":"San Francisco"},{"tags":[],"id":724711076332335104,"text":"@childpsychmom Kudos for your post: https://t.co/47unVi1OIB.  Consider my ebook No Touching Secrets! as a #prevention resource for families!","keywords":["prevention"],"urls":["http://tinyurl.com/grv6yjp"],"user_verified":false,"class":"Unclassified","date":"2016-04-25T09:25:59Z","lang":"en","retweets":0,"city":"San Francisco"},{"tags":["sexual assault","assault","fire"],"id":724710537121030144,"text":"@ace2blue @gabrielmalor @BlueBoxDave @Dawnsfire Is there a case of this happening, anywhere? There are already laws against sexual assault.","keywords":[],"urls":[],"user_verified":false,"class":"Rape","date":"2016-04-25T09:23:51Z","lang":"en","retweets":0,"city":"San Francisco"},{"tags":["abuse"],"id":724704449248169984,"text":"A look at the men accusing Dennis Hastert of sexual abuse: CHICAGO (AP) \u2014 When he steps before a judge Wednesd... https://t.co/yxOPKsl8ur","keywords":[],"urls":["http://yhoo.it/1NtWolz"],"user_verified":false,"class":"Rape","date":"2016-04-25T08:59:39Z","lang":"en","retweets":0,"city":"San Francisco"},{"tags":["sexual assault","assault"],"id":724701582814662656,"text":"Jian Ghomeshi trial: prosecutors will not appeal acquittal in sexual assault case https://t.co/6kigEfiZCi","keywords":[],"urls":["http://gu.com/p/4tj6y/stw"],"geo_location":"GeoLocation{latitude=37.80868612, longitude=-122.25614813}","user_verified":false,"class":"Rape","date":"2016-04-25T08:48:16Z","lang":"en","retweets":0,"city":"San Francisco"},{"tags":[],"id":724700972077867008,"text":"Bill Cosby loses appeal as court rules criminal prosecution can proceed https://t.co/bSikdOpfO2","keywords":[],"urls":["http://gu.com/p/4tj7j/stw"],"user_verified":false,"class":"Unclassified","date":"2016-04-25T08:45:50Z","lang":"en","retweets":0,"city":"San Francisco"},{"tags":["rape","abuse"],"id":724700520791711744,"text":"As porn increases -> decreases in rape, domestic abuse. Correlation not causation. But still https://t.co/MkWoFkuMFb https://t.co/PImEHgPBH7","keywords":[],"urls":["http://www.theatlantic.com/politics/archive/2016/04/porn-culture/477099/"],"user_verified":false,"class":"Rape","date":"2016-04-25T08:44:03Z","lang":"en","retweets":0,"city":"San Francisco"},{"tags":["sexual assault","assault"],"id":724699642835824640,"text":"RT @SSU_1961: It's on all of us to stop sexual assault. #SonomaState took the pledge to be a part of the solution and you can too https://t\u2026","keywords":["SonomaState"],"urls":["http://bit.ly/1HmA1bI"],"user_verified":false,"class":"Rape","date":"2016-04-25T08:40:33Z","lang":"en","retweets":2,"city":"San Francisco"},{"tags":[],"id":724699557976637440,"text":"Bill Cosby loses appeal as court rules criminal prosecution can proceed https://t.co/dqr7A7VP5l","keywords":[],"urls":["http://gu.com/p/4tj7j/stw"],"geo_location":"GeoLocation{latitude=37.80859526, longitude=-122.25663789}","user_verified":false,"class":"Unclassified","date":"2016-04-25T08:40:13Z","lang":"en","retweets":0,"city":"San Francisco"},{"tags":["sexual assault","assault"],"id":724698849227485188,"text":"New story from People in News : Bill Cosby's Sexual Assault Case Can Proceed, Pennsylvania Appeals Court Rules","keywords":[],"urls":[],"user_verified":false,"class":"Rape","date":"2016-04-25T08:37:24Z","lang":"en","retweets":0,"city":"San Francisco"},{"tags":["abuse"],"id":724698703706075137,"text":"Police arrest California minister in sexual abuse case - SFGate.. Related Articles: https://t.co/AbNRKxuMr0","keywords":[],"urls":["http://bit.ly/21bLXFM"],"user_verified":false,"class":"Rape","date":"2016-04-25T08:36:49Z","lang":"en","retweets":0,"city":"San Francisco"},{"tags":["sexual assault","assault"],"id":724697325021470720,"text":"#lawyer accused of having #sex with QC in broad daylight could face sexual assault  @judge_zone \nhttps://t.co/S1D4zI9jk9","keywords":["lawyer","sex"],"urls":["http://snip.ly/ei4b0"],"user_verified":false,"class":"Rape","date":"2016-04-25T08:31:21Z","lang":"en","retweets":0,"city":"San Francisco"},{"tags":["rape","rapist"],"id":724694464585936898,"text":"Rapist Jihadi Gang Rapes 14 yr old Girl Gets Community Service https://t.co/yTGeGkZ9ho..|tA","keywords":[],"urls":["https://www.therealstrategy.com/rape-victim-gets-ptsd-jihadis-get-community-service/"],"user_verified":false,"class":"Rape","date":"2016-04-25T08:19:59Z","lang":"en","retweets":0,"city":"San Francisco"},{"tags":["rape","rapist"],"id":724694176248520708,"text":"Rapist Jihadi Gang Rapes 14 yr old Girl Gets Community Service https://t.co/ORkknkJevn..|sS","keywords":[],"urls":["https://www.therealstrategy.com/rape-victim-gets-ptsd-jihadis-get-community-service/"],"user_verified":false,"class":"Rape","date":"2016-04-25T08:18:50Z","lang":"en","retweets":0,"city":"San Francisco"},{"tags":["sexual assault","assault"],"id":724692596178608128,"text":"Celeste Thorson: Bill Cosby's Sexual Assault Case Can Proceed, Pennsylvania Appeals Court Rules: Cosby's attor...  https://t.co/RfaD6euBKc","keywords":[],"urls":["http://su.pr/1ZEIRT"],"user_verified":false,"class":"Rape","date":"2016-04-25T08:12:33Z","lang":"en","retweets":0,"city":"San Francisco"},{"tags":["sexual assault","assault"],"id":724689592444686337,"text":"It's on all of us to stop sexual assault. #SonomaState took the pledge to be a part of the solution and you can too https://t.co/kuPt0npX5j","keywords":["SonomaState"],"urls":["http://bit.ly/1HmA1bI"],"user_verified":false,"class":"Rape","date":"2016-04-25T08:00:37Z","lang":"en","retweets":2,"city":"San Francisco"},{"tags":[],"id":724689372948385792,"text":"Check us out on \"Up and Out\" your guide to all cool things happening in the bay area.... https://t.co/b7Pmqec6Ua","keywords":[],"urls":["http://fb.me/3WvoKoR3U"],"user_verified":false,"class":"Unclassified","date":"2016-04-25T07:59:45Z","lang":"en","retweets":0,"city":"San Francisco"},{"tags":["abuse"],"id":724688667055390721,"text":"RT @mercnews: Dennis Hastert's four accusers: How they described alleged sexual abuse https://t.co/1OzmQVfDUA https://t.co/bxlAMq0BiD","keywords":[],"urls":["http://bayareane.ws/1So1S1G"],"user_verified":false,"class":"Rape","date":"2016-04-25T07:56:56Z","lang":"en","retweets":2,"city":"San Francisco"},{"tags":["abuse"],"id":724686397140033537,"text":"RT @ESTBLSHMNT: It's not just the Catholic Church whose leaders hurt their flock. Inside sexual abuses within American Zen Buddhism.\nhttps:\u2026","keywords":[],"urls":["http://www.theestablishment.co/2016/04/25/when-spiritual-leaders-abuse/"],"user_verified":false,"class":"Rape","date":"2016-04-25T07:47:55Z","lang":"en","retweets":7,"city":"San Francisco"},{"tags":["abuse"],"id":724685944171954176,"text":"Dennis Hastert's four accusers: How they described alleged sexual abuse https://t.co/1OzmQVfDUA https://t.co/bxlAMq0BiD","keywords":[],"urls":["http://bayareane.ws/1So1S1G"],"user_verified":true,"class":"Rape","date":"2016-04-25T07:46:07Z","lang":"en","retweets":2,"city":"San Francisco"},{"tags":["sexual assault","assault"],"id":724683067391008768,"text":"Tell Congress that you will #RiseUp with 25 million sexual assault survivors! Join @RiseNowUS's movement: https://t.co/dA7ZajgsA9","keywords":["RiseUp"],"urls":["http://chn.ge/22WqIah"],"user_verified":false,"class":"Rape","date":"2016-04-25T07:34:41Z","lang":"en","retweets":0,"city":"San Francisco"},{"tags":["sexual assault","assault"],"id":724682652545105921,"text":"Join Take Back The Night to raise awareness and shatter silence surrounding sexual assault! https://t.co/jsvkGndVWq https://t.co/wB4HVSrBha","keywords":[],"urls":["http://buff.ly/1VqwNgl"],"user_verified":false,"class":"Rape","date":"2016-04-25T07:33:02Z","lang":"en","retweets":0,"city":"San Francisco"},{"tags":["abuse"],"id":724679953015402496,"text":"RT @ESTBLSHMNT: It's not just the Catholic Church whose leaders hurt their flock. Inside sexual abuses within American Zen Buddhism.\nhttps:\u2026","keywords":[],"urls":["http://www.theestablishment.co/2016/04/25/when-spiritual-leaders-abuse/"],"user_verified":false,"class":"Rape","date":"2016-04-25T07:22:19Z","lang":"en","retweets":7,"city":"San Francisco"},{"tags":["rape","assault"],"id":724663470386515968,"text":"RT @RishiDarshan: Girl's medical report proves - \n'Rape/assault was NOT done' \n#Bail_बापूजीका_अधिकार \nhttps://t.co/DOibrIbbjW","keywords":["Bail_बापूजीका_अधिकार"],"urls":["https://www.youtube.com/watch?v=7kp2pQDH2EQ"],"user_verified":false,"class":"Rape","date":"2016-04-25T06:16:49Z","lang":"en","retweets":179,"city":"San Francisco"},{"tags":["rape","assault"],"id":724663272616525825,"text":"RT @RishiDarshan: Girl's medical report proves - \n'Rape/assault was NOT done' \n#Bail_बापूजीका_अधिकार \nhttps://t.co/DOibrIbbjW","keywords":["Bail_बापूजीका_अधिकार"],"urls":["https://www.youtube.com/watch?v=7kp2pQDH2EQ"],"user_verified":false,"class":"Rape","date":"2016-04-25T06:16:02Z","lang":"en","retweets":179,"city":"San Francisco"},{"tags":["abuse"],"id":724660234514501632,"text":"A look at the men accusing #Dennis #Hastert of sexual abuse https://t.co/AJwVLMo3gf https://t.co/qetjK8sdnb","keywords":["Dennis","Hastert"],"urls":["http://jenke.rs/v5J0Vp"],"user_verified":false,"class":"Rape","date":"2016-04-25T06:03:58Z","lang":"en","retweets":0,"city":"San Francisco"},{"tags":["abuse"],"id":724659315601088513,"text":"A look at the men accusing Dennis Hastert of sexual abuse https://t.co/aqTDbxan46","keywords":[],"urls":["http://dlvr.it/L8Nr7M"],"user_verified":false,"class":"Rape","date":"2016-04-25T06:00:19Z","lang":"en","retweets":0,"city":"San Francisco"},{"tags":["sexual assault","assault"],"id":724656327700537344,"text":"watch the sexual assault stats... https://t.co/rAC4ZhxR71","keywords":[],"urls":["https://twitter.com/Heritage/status/724291065377771521"],"user_verified":false,"class":"Rape","date":"2016-04-25T05:48:26Z","lang":"en","retweets":0,"city":"San Francisco"},{"tags":["abuse"],"id":724655097616031744,"text":"A look at the men accusing Dennis Hastert of sexual abuse: CHICAGO (AP) \u2014 When he steps before a judge Wednesd... https://t.co/2andUlXSs2","keywords":[],"urls":["http://tinyurl.com/gtz7d37"],"user_verified":false,"class":"Rape","date":"2016-04-25T05:43:33Z","lang":"en","retweets":0,"city":"San Francisco"},{"tags":["rape","rapist"],"id":724654616063803393,"text":"The Vatican Just Put a Convicted Rapist Back in a Parish   https://t.co/aU6ubg4NC1 via @thedailybeast #religion #Vatican #rape #spotlight","keywords":["religion","Vatican","rape","spotlight"],"urls":["http://thebea.st/2199Y0p"],"user_verified":false,"class":"Rape","date":"2016-04-25T05:41:38Z","lang":"en","retweets":0,"city":"San Francisco"},{"tags":["assault"],"id":724653103648116736,"text":"UC Berkeley: Expert questions if athletics department is doing enough to combat sexual harassment and assault... https://t.co/gVF0OVMkPF","keywords":[],"urls":["http://fb.me/5jXkuNQd7"],"user_verified":false,"class":"Assault","date":"2016-04-25T05:35:37Z","lang":"en","retweets":0,"city":"San Francisco"},{"tags":["eliminate","assault"],"id":724644569963327489,"text":"Walk to eliminate sexual assault https://t.co/fEDNnHtDSJ","keywords":[],"urls":["http://www.mtdemocrat.com/prospecting/walk-to-eliminate-sexual-assault/"],"user_verified":false,"class":"Murder","date":"2016-04-25T05:01:43Z","lang":"en","retweets":0,"city":"San Francisco"},{"tags":["rape","sexual assault","assault"],"id":724643402713686017,"text":"SART is a sexual assault survivor-sensitive program team\nhttps://t.co/pvdUjCL7Oq\u2026/sexual-assault-rape/sart https://t.co/pwpmNaEMRB","keywords":[],"urls":["http://www.peaceoverviolence.org/"],"user_verified":false,"class":"Rape","date":"2016-04-25T04:57:05Z","lang":"en","retweets":0,"city":"San Francisco"},{"tags":[],"id":724640434962591744,"text":"We often equate romantic relationships with consent... Read this post from @womenshealth https://t.co/eQxQ4cVfNB https://t.co/9ULK510XsD","keywords":[],"urls":["http://1.usa.gov/1Qx9Ks2"],"user_verified":false,"class":"Unclassified","date":"2016-04-25T04:45:17Z","lang":"en","retweets":0,"city":"San Francisco"},{"tags":["abuse"],"id":724636363098710017,"text":"RT @ESTBLSHMNT: It's not just the Catholic Church whose leaders hurt their flock. Inside sexual abuses within American Zen Buddhism.\nhttps:\u2026","keywords":[],"urls":["http://www.theestablishment.co/2016/04/25/when-spiritual-leaders-abuse/"],"user_verified":false,"class":"Rape","date":"2016-04-25T04:29:06Z","lang":"en","retweets":7,"city":"San Francisco"},{"tags":["abuse"],"id":724633650009018371,"text":"It's not just the Catholic Church whose leaders hurt their flock. Inside sexual abuses within American Zen Buddhism.\nhttps://t.co/YUF06jGF9K","keywords":[],"urls":["http://www.theestablishment.co/2016/04/25/when-spiritual-leaders-abuse/"],"user_verified":false,"class":"Rape","date":"2016-04-25T04:18:19Z","lang":"en","retweets":7,"city":"San Francisco"},{"tags":["sexual assault","assault"],"id":724631861356417025,"text":"Sexual Assault Can Happen in Relationships, Too | Office on Women's Health Blog https://t.co/t7TCsNaLqI","keywords":[],"urls":["http://www.womenshealth.gov/blog/sexual-assault-relationships.html#.Vx5BnSxf3Z4.twitter"],"user_verified":false,"class":"Rape","date":"2016-04-25T04:11:13Z","lang":"en","retweets":0,"city":"San Francisco"},{"tags":["sexual assault","assault"],"id":724623875632443392,"text":"RT @SFPD: #SFPD Resolution Regarding Reporting of Data Related to Sexual Assault Kits: https://t.co/Vq6E4XEISb","keywords":["SFPD"],"urls":["http://sanfranciscopolice.org/resolution-regarding-reporting-data-related-sexual-assault-kits"],"user_verified":false,"class":"Rape","date":"2016-04-25T03:39:29Z","lang":"en","retweets":3,"city":"San Francisco"},{"tags":["sexual assault","assault"],"id":724623011001720832,"text":"RT @KTVU: Baptist minister held in Martinez jail on sexual assault charges involving minor. https://t.co/i40rwUYiEK https://t.co/fbBdlMgrjZ","keywords":[],"urls":["http://bit.ly/1QwKW3q"],"user_verified":false,"class":"Rape","date":"2016-04-25T03:36:03Z","lang":"en","retweets":2,"city":"San Francisco"},{"tags":["abuse"],"id":724614995934224384,"text":"@PoliticAlBor 90% of sexual abuse of children is perpetrated by someone known to the victim, but ur crusading on twitter against...","keywords":[],"urls":[],"user_verified":false,"class":"Rape","date":"2016-04-25T03:04:12Z","lang":"en","retweets":0,"city":"San Francisco"},{"tags":["abuse"],"id":724614125112819714,"text":"@PoliticAlBor or, hey, while we're at it, how about homes w/ children, where the overwhelming majority of childhood sexual abuse happens?","keywords":[],"urls":[],"user_verified":false,"class":"Rape","date":"2016-04-25T03:00:44Z","lang":"en","retweets":0,"city":"San Francisco"},{"tags":["abuse"],"id":724610798098612224,"text":"Sexual Abuse Survivors Want Conservative Politicians To Knock It Off With 'Bathroom Predator' Myth https://t.co/Z05hqJu29z","keywords":[],"urls":["http://www.huffingtonpost.com/entry/sexual-assault-bathroom-law_us_57190d25e4b0d912d5fdda6b?ir=Queer+Voices&section=us_queer-voices&utm_hp_ref=queer-voices"],"user_verified":false,"class":"Rape","date":"2016-04-25T02:47:31Z","lang":"en","retweets":0,"city":"San Francisco"},{"tags":["sexual assault","assault"],"id":724606154433646592,"text":"RT @KTVU: Baptist minister held in Martinez jail on sexual assault charges involving minor. https://t.co/i40rwUYiEK https://t.co/fbBdlMgrjZ","keywords":[],"urls":["http://bit.ly/1QwKW3q"],"user_verified":false,"class":"Rape","date":"2016-04-25T02:29:04Z","lang":"en","retweets":2,"city":"San Francisco"},{"tags":["rape","rapist"],"id":724605745019404288,"text":"Rapist Jihadi Gang Rapes 14 yr old Girl Gets Community Service https://t.co/yTGeGkZ9ho.|tA","keywords":[],"urls":["https://www.therealstrategy.com/rape-victim-gets-ptsd-jihadis-get-community-service/"],"user_verified":false,"class":"Rape","date":"2016-04-25T02:27:26Z","lang":"en","retweets":0,"city":"San Francisco"},{"tags":["sexual assault","assault","speeding"],"id":724605614152814594,"text":"This kind-hearted cop let a drunken, speeding teen go with a sexual assault instead of a DWI.  #realisticcopaganda","keywords":["realisticcopaganda"],"urls":[],"user_verified":false,"class":"Rape","date":"2016-04-25T02:26:55Z","lang":"en","retweets":0,"city":"San Francisco"},{"tags":["rape","rapist"],"id":724605518682140672,"text":"Rapist Jihadi Gang Rapes 14 yr old Girl Gets Community Service https://t.co/ORkknkJevn.|sS","keywords":[],"urls":["https://www.therealstrategy.com/rape-victim-gets-ptsd-jihadis-get-community-service/"],"user_verified":false,"class":"Rape","date":"2016-04-25T02:26:32Z","lang":"en","retweets":0,"city":"San Francisco"},{"tags":["sexual assault","assault"],"id":724605091672547328,"text":"RT @neopetmom: if ur worried abt sexual assault entailing, raise awareness about sexual assault. a bathroom isn't the problem here https://\u2026","keywords":[],"urls":["https://twitter.com/mrestrepo172/status/724458178138771456"],"user_verified":false,"class":"Rape","date":"2016-04-25T02:24:51Z","lang":"en","retweets":52,"city":"San Francisco"},{"tags":["sexual assault","assault"],"id":724594942648131584,"text":"RT @neopetmom: if ur worried abt sexual assault entailing, raise awareness about sexual assault. a bathroom isn't the problem here https://\u2026","keywords":[],"urls":["https://twitter.com/mrestrepo172/status/724458178138771456"],"user_verified":false,"class":"Rape","date":"2016-04-25T01:44:31Z","lang":"en","retweets":52,"city":"San Francisco"},{"tags":["sexual assault","assault"],"id":724592090328391680,"text":"RT @neopetmom: if ur worried abt sexual assault entailing, raise awareness about sexual assault. a bathroom isn't the problem here https://\u2026","keywords":[],"urls":["https://twitter.com/mrestrepo172/status/724458178138771456"],"user_verified":false,"class":"Rape","date":"2016-04-25T01:33:11Z","lang":"en","retweets":52,"city":"San Francisco"},{"tags":["sexual assault","assault"],"id":724591376537546753,"text":"Baptist minister held in Martinez jail on sexual assault charges involving minor. https://t.co/i40rwUYiEK https://t.co/fbBdlMgrjZ","keywords":[],"urls":["http://bit.ly/1QwKW3q"],"user_verified":true,"class":"Rape","date":"2016-04-25T01:30:21Z","lang":"en","retweets":2,"city":"San Francisco"},{"tags":["sexual assault","assault"],"id":724590273418956804,"text":"RT @neopetmom: if ur worried abt sexual assault entailing, raise awareness about sexual assault. a bathroom isn't the problem here https://\u2026","keywords":[],"urls":["https://twitter.com/mrestrepo172/status/724458178138771456"],"user_verified":false,"class":"Rape","date":"2016-04-25T01:25:58Z","lang":"en","retweets":52,"city":"San Francisco"},{"tags":["sexual assault","assault"],"id":724583277986603008,"text":"RT @neopetmom: if ur worried abt sexual assault entailing, raise awareness about sexual assault. a bathroom isn't the problem here https://\u2026","keywords":[],"urls":["https://twitter.com/mrestrepo172/status/724458178138771456"],"user_verified":false,"class":"Rape","date":"2016-04-25T12:58:10Z","lang":"en","retweets":52,"city":"San Francisco"},{"tags":["sexual assault","assault"],"id":724573269194473472,"text":"RT @neopetmom: if ur worried abt sexual assault entailing, raise awareness about sexual assault. a bathroom isn't the problem here https://\u2026","keywords":[],"urls":["https://twitter.com/mrestrepo172/status/724458178138771456"],"user_verified":false,"class":"Rape","date":"2016-04-25T12:18:23Z","lang":"en","retweets":52,"city":"San Francisco"},{"tags":["sexual assault","assault"],"id":724571365588779008,"text":"RT @neopetmom: if ur worried abt sexual assault entailing, raise awareness about sexual assault. a bathroom isn't the problem here https://\u2026","keywords":[],"urls":["https://twitter.com/mrestrepo172/status/724458178138771456"],"user_verified":false,"class":"Rape","date":"2016-04-25T12:10:50Z","lang":"en","retweets":52,"city":"San Francisco"},{"tags":["sexual assault","assault"],"id":724557374128795648,"text":"RT @neopetmom: if ur worried abt sexual assault entailing, raise awareness about sexual assault. a bathroom isn't the problem here https://\u2026","keywords":[],"urls":["https://twitter.com/mrestrepo172/status/724458178138771456"],"user_verified":false,"class":"Rape","date":"2016-04-25T11:15:14Z","lang":"en","retweets":52,"city":"San Francisco"},{"tags":["rape","rapist"],"id":724514763477254144,"text":"Rapist Jihadi Gang Rapes 14 yr old Girl Gets Community Service https://t.co/yTGeGkZ9ho|tA","keywords":[],"urls":["https://www.therealstrategy.com/rape-victim-gets-ptsd-jihadis-get-community-service/"],"user_verified":false,"class":"Rape","date":"2016-04-25T08:25:55Z","lang":"en","retweets":0,"city":"San Francisco"},{"tags":["abuse"],"id":724514466742820864,"text":"Police arrest California minister in sexual abuse case - SFGate.. Related Articles: https://t.co/AbNRKxuMr0","keywords":[],"urls":["http://bit.ly/21bLXFM"],"user_verified":false,"class":"Rape","date":"2016-04-25T08:24:44Z","lang":"en","retweets":0,"city":"San Francisco"},{"tags":["rape","rapist"],"id":724514425575710721,"text":"Rapist Jihadi Gang Rapes 14 yr old Girl Gets Community Service https://t.co/ORkknkJevn|sS","keywords":[],"urls":["https://www.therealstrategy.com/rape-victim-gets-ptsd-jihadis-get-community-service/"],"user_verified":false,"class":"Rape","date":"2016-04-25T08:24:34Z","lang":"en","retweets":0,"city":"San Francisco"},{"tags":["sexual assault","assault"],"id":724494926570917888,"text":"If I go to the mall and chill on a bench and whip my dick out is that sexual assault toward anyone...nah Ima do it this weekend then","keywords":[],"urls":[],"user_verified":false,"class":"Rape","date":"2016-04-25T07:07:05Z","lang":"en","retweets":0,"city":"San Francisco"},{"tags":["sexual assault","assault"],"id":724492953352171520,"text":"RT @neopetmom: if ur worried abt sexual assault entailing, raise awareness about sexual assault. a bathroom isn't the problem here https://\u2026","keywords":[],"urls":["https://twitter.com/mrestrepo172/status/724458178138771456"],"user_verified":false,"class":"Rape","date":"2016-04-25T06:59:15Z","lang":"en","retweets":52,"city":"San Francisco"},{"tags":["sexual assault","assault"],"id":724491574856417280,"text":"RT @neopetmom: if ur worried abt sexual assault entailing, raise awareness about sexual assault. a bathroom isn't the problem here https://\u2026","keywords":[],"urls":["https://twitter.com/mrestrepo172/status/724458178138771456"],"user_verified":false,"class":"Rape","date":"2016-04-25T06:53:46Z","lang":"en","retweets":52,"city":"San Francisco"},{"tags":["sexual assault","assault"],"id":724490031977533440,"text":"RT @neopetmom: if ur worried abt sexual assault entailing, raise awareness about sexual assault. a bathroom isn't the problem here https://\u2026","keywords":[],"urls":["https://twitter.com/mrestrepo172/status/724458178138771456"],"user_verified":false,"class":"Rape","date":"2016-04-25T06:47:38Z","lang":"en","retweets":52,"city":"San Francisco"},{"tags":["sexual assault","assault"],"id":724484833259352065,"text":"RT @neopetmom: if ur worried abt sexual assault entailing, raise awareness about sexual assault. a bathroom isn't the problem here https://\u2026","keywords":[],"urls":["https://twitter.com/mrestrepo172/status/724458178138771456"],"user_verified":false,"class":"Rape","date":"2016-04-25T06:26:59Z","lang":"en","retweets":52,"city":"San Francisco"},{"tags":["sexual assault","assault"],"id":724483660217360384,"text":"RT @neopetmom: if ur worried abt sexual assault entailing, raise awareness about sexual assault. a bathroom isn't the problem here https://\u2026","keywords":[],"urls":["https://twitter.com/mrestrepo172/status/724458178138771456"],"user_verified":false,"class":"Rape","date":"2016-04-25T06:22:19Z","lang":"en","retweets":52,"city":"San Francisco"},{"tags":["sexual assault","assault"],"id":724479911545573376,"text":"RT @neopetmom: if ur worried abt sexual assault entailing, raise awareness about sexual assault. a bathroom isn't the problem here https://\u2026","keywords":[],"urls":["https://twitter.com/mrestrepo172/status/724458178138771456"],"user_verified":false,"class":"Rape","date":"2016-04-25T06:07:25Z","lang":"en","retweets":52,"city":"San Francisco"},{"tags":["sexual assault","assault"],"id":724479460846661633,"text":"RT @neopetmom: if ur worried abt sexual assault entailing, raise awareness about sexual assault. a bathroom isn't the problem here https://\u2026","keywords":[],"urls":["https://twitter.com/mrestrepo172/status/724458178138771456"],"user_verified":false,"class":"Rape","date":"2016-04-25T06:05:38Z","lang":"en","retweets":52,"city":"San Francisco"},{"tags":["sexual assault","assault"],"id":724479452369952768,"text":"RT @neopetmom: if ur worried abt sexual assault entailing, raise awareness about sexual assault. a bathroom isn't the problem here https://\u2026","keywords":[],"urls":["https://twitter.com/mrestrepo172/status/724458178138771456"],"user_verified":false,"class":"Rape","date":"2016-04-25T06:05:36Z","lang":"en","retweets":52,"city":"San Francisco"},{"tags":["sexual assault","assault"],"id":724478620173930496,"text":"RT @neopetmom: if ur worried abt sexual assault entailing, raise awareness about sexual assault. a bathroom isn't the problem here https://\u2026","keywords":[],"urls":["https://twitter.com/mrestrepo172/status/724458178138771456"],"user_verified":false,"class":"Rape","date":"2016-04-25T06:02:17Z","lang":"en","retweets":52,"city":"San Francisco"},{"tags":["sexual assault","assault"],"id":724476190820454400,"text":"RT @neopetmom: if ur worried abt sexual assault entailing, raise awareness about sexual assault. a bathroom isn't the problem here https://\u2026","keywords":[],"urls":["https://twitter.com/mrestrepo172/status/724458178138771456"],"user_verified":false,"class":"Rape","date":"2016-04-25T05:52:38Z","lang":"en","retweets":52,"city":"San Francisco"},{"tags":["sexual assault","assault"],"id":724475522973986816,"text":"Some lawmakers are urging U.S. News to add sexual assault rates to its college rankings. https://t.co/D3OaHT2xab","keywords":[],"urls":["http://fb.me/2c8RC33qv"],"user_verified":false,"class":"Rape","date":"2016-04-25T05:49:59Z","lang":"en","retweets":0,"city":"San Francisco"},{"tags":["sexual assault","assault"],"id":724473959928877056,"text":"RT @neopetmom: if ur worried abt sexual assault entailing, raise awareness about sexual assault. a bathroom isn't the problem here https://\u2026","keywords":[],"urls":["https://twitter.com/mrestrepo172/status/724458178138771456"],"user_verified":false,"class":"Rape","date":"2016-04-25T05:43:46Z","lang":"en","retweets":52,"city":"San Francisco"},{"tags":["sexual assault","assault"],"id":724472090275934209,"text":"RT @neopetmom: if ur worried abt sexual assault entailing, raise awareness about sexual assault. a bathroom isn't the problem here https://\u2026","keywords":[],"urls":["https://twitter.com/mrestrepo172/status/724458178138771456"],"user_verified":false,"class":"Rape","date":"2016-04-25T05:36:21Z","lang":"en","retweets":52,"city":"San Francisco"},{"tags":["sexual assault","assault"],"id":724471340229521408,"text":"RT @neopetmom: if ur worried abt sexual assault entailing, raise awareness about sexual assault. a bathroom isn't the problem here https://\u2026","keywords":[],"urls":["https://twitter.com/mrestrepo172/status/724458178138771456"],"user_verified":false,"class":"Rape","date":"2016-04-25T05:33:22Z","lang":"en","retweets":52,"city":"San Francisco"},{"tags":["sexual assault","assault"],"id":724470601889550336,"text":"RT @neopetmom: if ur worried abt sexual assault entailing, raise awareness about sexual assault. a bathroom isn't the problem here https://\u2026","keywords":[],"urls":["https://twitter.com/mrestrepo172/status/724458178138771456"],"user_verified":false,"class":"Rape","date":"2016-04-25T05:30:26Z","lang":"en","retweets":52,"city":"San Francisco"},{"tags":["sexual assault","assault"],"id":724470293985554432,"text":"RT @neopetmom: if ur worried abt sexual assault entailing, raise awareness about sexual assault. a bathroom isn't the problem here https://\u2026","keywords":[],"urls":["https://twitter.com/mrestrepo172/status/724458178138771456"],"user_verified":false,"class":"Rape","date":"2016-04-25T05:29:12Z","lang":"en","retweets":52,"city":"San Francisco"},{"tags":["sexual assault","assault"],"id":724469762433015808,"text":"RT @neopetmom: if ur worried abt sexual assault entailing, raise awareness about sexual assault. a bathroom isn't the problem here https://\u2026","keywords":[],"urls":["https://twitter.com/mrestrepo172/status/724458178138771456"],"user_verified":false,"class":"Rape","date":"2016-04-25T05:27:06Z","lang":"en","retweets":52,"city":"San Francisco"},{"tags":["assault"],"id":724469727159029760,"text":"UC Berkeley: Expert questions if athletics department is doing enough to combat sexual harassment and assault .. https://t.co/PWnIWwwuSr","keywords":[],"urls":["http://dld.bz/e3qBC"],"user_verified":false,"class":"Assault","date":"2016-04-25T05:26:57Z","lang":"en","retweets":0,"city":"San Francisco"},{"tags":["sexual assault","assault"],"id":724469656929497088,"text":"RT @neopetmom: if ur worried abt sexual assault entailing, raise awareness about sexual assault. a bathroom isn't the problem here https://\u2026","keywords":[],"urls":["https://twitter.com/mrestrepo172/status/724458178138771456"],"user_verified":false,"class":"Rape","date":"2016-04-25T05:26:40Z","lang":"en","retweets":52,"city":"San Francisco"},{"tags":["sexual assault","assault"],"id":724467991102943233,"text":"RT @neopetmom: if ur worried abt sexual assault entailing, raise awareness about sexual assault. a bathroom isn't the problem here https://\u2026","keywords":[],"urls":["https://twitter.com/mrestrepo172/status/724458178138771456"],"user_verified":false,"class":"Rape","date":"2016-04-25T05:20:03Z","lang":"en","retweets":52,"city":"San Francisco"},{"tags":["sexual assault","assault"],"id":724467847607390208,"text":"RT @neopetmom: if ur worried abt sexual assault entailing, raise awareness about sexual assault. a bathroom isn't the problem here https://\u2026","keywords":[],"urls":["https://twitter.com/mrestrepo172/status/724458178138771456"],"user_verified":false,"class":"Rape","date":"2016-04-25T05:19:29Z","lang":"en","retweets":52,"city":"San Francisco"},{"tags":["sexual assault","assault"],"id":724467009702891520,"text":"RT @neopetmom: if ur worried abt sexual assault entailing, raise awareness about sexual assault. a bathroom isn't the problem here https://\u2026","keywords":[],"urls":["https://twitter.com/mrestrepo172/status/724458178138771456"],"user_verified":false,"class":"Rape","date":"2016-04-25T05:16:09Z","lang":"en","retweets":52,"city":"San Francisco"},{"tags":["assault"],"id":724466873153294336,"text":"UC Berkeley: Expert questions if athletics department is doing enough to combat sexual harassment and assault ... https://t.co/l7zcqC3PHC","keywords":[],"urls":["http://bayareane.ws/1YPoubU"],"user_verified":false,"class":"Assault","date":"2016-04-25T05:15:37Z","lang":"en","retweets":0,"city":"San Francisco"},{"tags":["sexual assault","assault"],"id":724466610862333953,"text":"RT @neopetmom: if ur worried abt sexual assault entailing, raise awareness about sexual assault. a bathroom isn't the problem here https://\u2026","keywords":[],"urls":["https://twitter.com/mrestrepo172/status/724458178138771456"],"user_verified":false,"class":"Rape","date":"2016-04-25T05:14:34Z","lang":"en","retweets":52,"city":"San Francisco"},{"tags":["sexual assault","assault"],"id":724466255978057728,"text":"RT @neopetmom: if ur worried abt sexual assault entailing, raise awareness about sexual assault. a bathroom isn't the problem here https://\u2026","keywords":[],"urls":["https://twitter.com/mrestrepo172/status/724458178138771456"],"user_verified":false,"class":"Rape","date":"2016-04-25T05:13:10Z","lang":"en","retweets":52,"city":"San Francisco"},{"tags":["sexual assault","assault"],"id":724465785221976068,"text":"RT @neopetmom: if ur worried abt sexual assault entailing, raise awareness about sexual assault. a bathroom isn't the problem here https://\u2026","keywords":[],"urls":["https://twitter.com/mrestrepo172/status/724458178138771456"],"user_verified":false,"class":"Rape","date":"2016-04-25T05:11:17Z","lang":"en","retweets":52,"city":"San Francisco"},{"tags":["sexual assault","assault"],"id":724465717165338626,"text":"RT @neopetmom: if ur worried abt sexual assault entailing, raise awareness about sexual assault. a bathroom isn't the problem here https://\u2026","keywords":[],"urls":["https://twitter.com/mrestrepo172/status/724458178138771456"],"user_verified":false,"class":"Rape","date":"2016-04-25T05:11:01Z","lang":"en","retweets":52,"city":"San Francisco"},{"tags":["sexual assault","assault"],"id":724465478790324224,"text":"RT @neopetmom: if ur worried abt sexual assault entailing, raise awareness about sexual assault. a bathroom isn't the problem here https://\u2026","keywords":[],"urls":["https://twitter.com/mrestrepo172/status/724458178138771456"],"user_verified":false,"class":"Rape","date":"2016-04-25T05:10:04Z","lang":"en","retweets":52,"city":"San Francisco"},{"tags":["sexual assault","assault"],"id":724465151638835200,"text":"RT @neopetmom: if ur worried abt sexual assault entailing, raise awareness about sexual assault. a bathroom isn't the problem here https://\u2026","keywords":[],"urls":["https://twitter.com/mrestrepo172/status/724458178138771456"],"user_verified":false,"class":"Rape","date":"2016-04-25T05:08:46Z","lang":"en","retweets":52,"city":"San Francisco"},{"tags":["sexual assault","assault"],"id":724465143527182336,"text":"RT @neopetmom: if ur worried abt sexual assault entailing, raise awareness about sexual assault. a bathroom isn't the problem here https://\u2026","keywords":[],"urls":["https://twitter.com/mrestrepo172/status/724458178138771456"],"user_verified":false,"class":"Rape","date":"2016-04-25T05:08:44Z","lang":"en","retweets":52,"city":"San Francisco"},{"tags":["sexual assault","assault"],"id":724464707550113792,"text":"RT @neopetmom: if ur worried abt sexual assault entailing, raise awareness about sexual assault. a bathroom isn't the problem here https://\u2026","keywords":[],"urls":["https://twitter.com/mrestrepo172/status/724458178138771456"],"user_verified":false,"class":"Rape","date":"2016-04-25T05:07:00Z","lang":"en","retweets":52,"city":"San Francisco"},{"tags":["sexual assault","assault"],"id":724464539928948736,"text":"RT @neopetmom: if ur worried abt sexual assault entailing, raise awareness about sexual assault. a bathroom isn't the problem here https://\u2026","keywords":[],"urls":["https://twitter.com/mrestrepo172/status/724458178138771456"],"user_verified":false,"class":"Rape","date":"2016-04-25T05:06:20Z","lang":"en","retweets":52,"city":"San Francisco"},{"tags":["sexual assault","assault"],"id":724464339848056832,"text":"RT @neopetmom: if ur worried abt sexual assault entailing, raise awareness about sexual assault. a bathroom isn't the problem here https://\u2026","keywords":[],"urls":["https://twitter.com/mrestrepo172/status/724458178138771456"],"user_verified":false,"class":"Rape","date":"2016-04-25T05:05:33Z","lang":"en","retweets":52,"city":"San Francisco"},{"tags":["sexual assault","assault"],"id":724464223732944896,"text":"RT @neopetmom: if ur worried abt sexual assault entailing, raise awareness about sexual assault. a bathroom isn't the problem here https://\u2026","keywords":[],"urls":["https://twitter.com/mrestrepo172/status/724458178138771456"],"user_verified":false,"class":"Rape","date":"2016-04-25T05:05:05Z","lang":"en","retweets":52,"city":"San Francisco"},{"tags":["sexual assault","assault"],"id":724464212789985280,"text":"RT @neopetmom: if ur worried abt sexual assault entailing, raise awareness about sexual assault. a bathroom isn't the problem here https://\u2026","keywords":[],"urls":["https://twitter.com/mrestrepo172/status/724458178138771456"],"user_verified":false,"class":"Rape","date":"2016-04-25T05:05:02Z","lang":"en","retweets":52,"city":"San Francisco"},{"tags":["assault"],"id":724463786074066944,"text":"UC Berkeley: Expert questions if athletics department is doing enough to combat sexual harassment and assault\u2026 https://t.co/O1F97HbYli","keywords":[],"urls":["http://m.tbnn.it/L84x8J"],"user_verified":false,"class":"Assault","date":"2016-04-25T05:03:21Z","lang":"en","retweets":0,"city":"San Francisco"},{"tags":["sexual assault","assault"],"id":724463715706249216,"text":"RT @neopetmom: if ur worried abt sexual assault entailing, raise awareness about sexual assault. a bathroom isn't the problem here https://\u2026","keywords":[],"urls":["https://twitter.com/mrestrepo172/status/724458178138771456"],"user_verified":false,"class":"Rape","date":"2016-04-25T05:03:04Z","lang":"en","retweets":52,"city":"San Francisco"}]