[{"tags":["speeding","ticket"],"id":724748134644092928,"text":"RT @alexparker6: \"I got a speeding ticket the other day\"\n@rayray_marie3 \"for what\"","keywords":[],"urls":[],"user_verified":false,"class":"Infractions","date":"2016-04-25T11:53:15Z","lang":"en","retweets":1,"city":"Atlanta"},{"tags":["speeding","ticket"],"id":724748065563877377,"text":"\"I got a speeding ticket the other day\"\n@rayray_marie3 \"for what\"","keywords":[],"urls":[],"user_verified":false,"class":"Infractions","date":"2016-04-25T11:52:58Z","lang":"en","retweets":1,"city":"Atlanta"},{"tags":["speeding","ticket"],"id":724740190829457408,"text":"When you have to come up with 200 in ten days for a speeding ticket?","keywords":[],"urls":[],"user_verified":false,"class":"Infractions","date":"2016-04-25T11:21:41Z","lang":"en","retweets":0,"city":"Atlanta"},{"tags":["speeding"],"id":724716818531758081,"text":"I swear it feels like Time is Speeding Up. Seems like less time available in a Day, then in the past... #alchemy!","keywords":["alchemy"],"urls":[],"user_verified":false,"class":"Infractions","date":"2016-04-25T09:48:48Z","lang":"en","retweets":0,"city":"Atlanta"},{"tags":["speeding","ticket"],"id":724714097678389248,"text":"RT @B__Mason: I used to haul ass everywhere I went until I realized most things aren't going anywhere. those speeding tickets also helped.","keywords":[],"urls":[],"user_verified":false,"class":"Infractions","date":"2016-04-25T09:38:00Z","lang":"en","retweets":1,"city":"Atlanta"},{"tags":["speeding","ticket"],"id":724706892392501248,"text":"I used to haul ass everywhere I went until I realized most things aren't going anywhere. those speeding tickets also helped.","keywords":[],"urls":[],"user_verified":false,"class":"Infractions","date":"2016-04-25T09:09:22Z","lang":"en","retweets":1,"city":"Atlanta"},{"tags":["speeding","ticket"],"id":724704925385678848,"text":"RT @JuanitaGrace: 😩RT @LilLarryLaflare: Only time a date $200 is when I get a $170 speeding ticket taking her home when she say she don't s\u2026","keywords":[],"urls":[],"user_verified":false,"class":"Infractions","date":"2016-04-25T09:01:33Z","lang":"en","retweets":6,"city":"Atlanta"},{"tags":["speeding"],"id":724702599723667456,"text":"Leap Of Faith: Damien Walters Backflip Over Speeding Formula E Car https://t.co/J5mF4VNhOD","keywords":[],"urls":["https://lnkd.in/bMgbx5e"],"user_verified":false,"class":"Infractions","predicted_location":"","date":"2016-04-25T08:52:18Z","lang":"en","retweets":0,"city":"Atlanta"},{"tags":["speeding","ticket"],"id":724700227827986432,"text":"RT @JuanitaGrace: 😩RT @LilLarryLaflare: Only time a date $200 is when I get a $170 speeding ticket taking her home when she say she don't s\u2026","keywords":[],"urls":[],"user_verified":false,"class":"Infractions","date":"2016-04-25T08:42:53Z","lang":"en","retweets":6,"city":"Atlanta"},{"tags":["speeding","ticket"],"id":724699794946420737,"text":"RT @JuanitaGrace: 😩RT @LilLarryLaflare: Only time a date $200 is when I get a $170 speeding ticket taking her home when she say she don't s\u2026","keywords":[],"urls":[],"user_verified":false,"class":"Infractions","date":"2016-04-25T08:41:10Z","lang":"en","retweets":6,"city":"Atlanta"},{"tags":["speeding","ticket"],"id":724698648232136704,"text":"RT @JuanitaGrace: 😩RT @LilLarryLaflare: Only time a date $200 is when I get a $170 speeding ticket taking her home when she say she don't s\u2026","keywords":[],"urls":[],"user_verified":false,"class":"Infractions","date":"2016-04-25T08:36:36Z","lang":"en","retweets":6,"city":"Atlanta"},{"tags":["speeding","ticket"],"id":724698579244212224,"text":"RT @JuanitaGrace: 😩RT @LilLarryLaflare: Only time a date $200 is when I get a $170 speeding ticket taking her home when she say she don't s\u2026","keywords":[],"urls":[],"user_verified":false,"class":"Infractions","date":"2016-04-25T08:36:20Z","lang":"en","retweets":6,"city":"Atlanta"},{"tags":["speeding","ticket"],"id":724697859954741248,"text":"😩RT @LilLarryLaflare: Only time a date $200 is when I get a $170 speeding ticket taking her home when she say she don't suck dick....","keywords":[],"urls":[],"user_verified":false,"class":"Infractions","date":"2016-04-25T08:33:28Z","lang":"en","retweets":6,"city":"Atlanta"},{"tags":["speeding"],"id":724682986852110337,"text":"Leap Of Faith: Damien Walters Backflip Over Speeding Formula E Car https://t.co/g1fau5Jtkf via @YouTube","keywords":[],"urls":["https://youtu.be/EF9bbY3-lQU"],"user_verified":false,"class":"Infractions","predicted_location":"","date":"2016-04-25T07:34:22Z","lang":"en","retweets":0,"city":"Atlanta"},{"tags":["hit","speeding"],"id":724666821241008128,"text":"Police: Two Dead After Speeding Car Hits Tree https://t.co/4jZBAZxl5u","keywords":[],"urls":["http://dlvr.it/L8PK7V"],"user_verified":false,"class":"Assault","date":"2016-04-25T06:30:08Z","lang":"en","retweets":0,"city":"Atlanta"},{"tags":["jaywalking"],"id":724665770500861952,"text":"RT @fauxHC_Smart: HEY UGA PD PRETTY SURE I JUST SAW A 3RD TEAM PLACEKICK HOLDER JAYWALKING IN FRONT OF COLISEUM QUICK BETTER CALL IN THE SW\u2026","keywords":[],"urls":[],"user_verified":false,"class":"Infractions","date":"2016-04-25T06:25:57Z","lang":"en","retweets":8,"city":"Atlanta"},{"tags":["hit","speeding"],"id":724663307127279616,"text":"Police: Two Dead After Speeding Car Hits Tree https://t.co/N6vMHlIG55 https://t.co/jaSJttluOT","keywords":[],"urls":["http://dlvr.it/L8P5y4"],"user_verified":false,"class":"Assault","date":"2016-04-25T06:16:10Z","lang":"en","retweets":0,"city":"Atlanta"},{"tags":["hit","speeding"],"id":724663298319208449,"text":"Police: Two Dead After Speeding Car Hits Tree https://t.co/9KDlmXczBW https://t.co/YoRAi20c4e","keywords":[],"urls":["http://dlvr.it/L8P5xt"],"user_verified":false,"class":"Assault","date":"2016-04-25T06:16:08Z","lang":"en","retweets":0,"city":"Atlanta"},{"tags":["hit","speeding"],"id":724663297820106752,"text":"Police: Two Dead After Speeding Car Hits Tree https://t.co/g0QnmjBWiI https://t.co/VSBoIwpWT2","keywords":[],"urls":["http://dlvr.it/L8P5yd"],"user_verified":false,"class":"Assault","date":"2016-04-25T06:16:08Z","lang":"en","retweets":0,"city":"Atlanta"},{"tags":["hit","speeding"],"id":724663294892503040,"text":"Police: Two Dead After Speeding Car Hits Tree https://t.co/IZWYgQ0Jhn https://t.co/cjLjuAlK3O","keywords":[],"urls":["http://dlvr.it/L8P5x1"],"user_verified":false,"class":"Assault","date":"2016-04-25T06:16:07Z","lang":"en","retweets":0,"city":"Atlanta"},{"tags":["hit","speeding"],"id":724661540612251649,"text":"Police: Two Dead After Speeding Car Hits Tree https://t.co/F973T06gZv https://t.co/ExLEW7DqOK","keywords":[],"urls":["http://dlvr.it/L8Nz3L"],"user_verified":false,"class":"Assault","date":"2016-04-25T06:09:09Z","lang":"en","retweets":0,"city":"Atlanta"},{"tags":["hit","speeding"],"id":724661028059910144,"text":"Police: Two Dead After Speeding Car Hits Tree https://t.co/iVyHjsMLoP","keywords":[],"urls":["http://dlvr.it/L8NxCP"],"user_verified":false,"class":"Assault","date":"2016-04-25T06:07:07Z","lang":"en","retweets":0,"city":"Atlanta"},{"tags":["jaywalking"],"id":724649284935782402,"text":"RT @fauxHC_Smart: HEY UGA PD PRETTY SURE I JUST SAW A 3RD TEAM PLACEKICK HOLDER JAYWALKING IN FRONT OF COLISEUM QUICK BETTER CALL IN THE SW\u2026","keywords":[],"urls":[],"user_verified":false,"class":"Infractions","date":"2016-04-25T05:20:27Z","lang":"en","retweets":8,"city":"Atlanta"},{"tags":["jaywalking"],"id":724647852845096961,"text":"RT @fauxHC_Smart: HEY UGA PD PRETTY SURE I JUST SAW A 3RD TEAM PLACEKICK HOLDER JAYWALKING IN FRONT OF COLISEUM QUICK BETTER CALL IN THE SW\u2026","keywords":[],"urls":[],"user_verified":false,"class":"Infractions","date":"2016-04-25T05:14:46Z","lang":"en","retweets":8,"city":"Atlanta"},{"tags":["speeding","ticket"],"id":724645747971506178,"text":"Speeding ticket 😡😡😡","keywords":[],"urls":[],"user_verified":false,"class":"Infractions","date":"2016-04-25T05:06:24Z","lang":"en","retweets":0,"city":"Atlanta"},{"tags":["jaywalking"],"id":724644254493106177,"text":"RT @fauxHC_Smart: HEY UGA PD PRETTY SURE I JUST SAW A 3RD TEAM PLACEKICK HOLDER JAYWALKING IN FRONT OF COLISEUM QUICK BETTER CALL IN THE SW\u2026","keywords":[],"urls":[],"user_verified":false,"class":"Infractions","date":"2016-04-25T05:00:28Z","lang":"en","retweets":8,"city":"Atlanta"},{"tags":["speeding"],"id":724638321746558976,"text":"Walking On Cars - Speeding Cars https://t.co/YJ97E60iEO #nowplaying #listenlive","keywords":["nowplaying","listenlive"],"urls":["http://rdo.to/WBMR"],"user_verified":false,"class":"Infractions","date":"2016-04-25T04:36:53Z","lang":"en","retweets":0,"city":"Atlanta"},{"tags":["speeding"],"id":724634875815444480,"text":"Be careful speeding on shallowford rd, POLICE ready to pull you over!!","keywords":[],"urls":[],"user_verified":false,"class":"Infractions","date":"2016-04-25T04:23:12Z","lang":"en","retweets":0,"city":"Atlanta"},{"tags":["jaywalking"],"id":724619448490024960,"text":"RT @fauxHC_Smart: HEY UGA PD PRETTY SURE I JUST SAW A 3RD TEAM PLACEKICK HOLDER JAYWALKING IN FRONT OF COLISEUM QUICK BETTER CALL IN THE SW\u2026","keywords":[],"urls":[],"user_verified":false,"class":"Infractions","date":"2016-04-25T03:21:53Z","lang":"en","retweets":8,"city":"Atlanta"},{"tags":["littering"],"id":724616807399743488,"text":"@SirLanik Lu Bu loves a good corpse littering.","keywords":[],"urls":[],"user_verified":false,"class":"Infractions","date":"2016-04-25T03:11:24Z","lang":"en","retweets":0,"city":"Atlanta"},{"tags":["jaywalking"],"id":724616074109562880,"text":"RT @fauxHC_Smart: HEY UGA PD PRETTY SURE I JUST SAW A 3RD TEAM PLACEKICK HOLDER JAYWALKING IN FRONT OF COLISEUM QUICK BETTER CALL IN THE SW\u2026","keywords":[],"urls":[],"user_verified":false,"class":"Infractions","date":"2016-04-25T03:08:29Z","lang":"en","retweets":8,"city":"Atlanta"},{"tags":["jaywalking"],"id":724615461824925696,"text":"HEY UGA PD PRETTY SURE I JUST SAW A 3RD TEAM PLACEKICK HOLDER JAYWALKING IN FRONT OF COLISEUM QUICK BETTER CALL IN THE SWAT TEAM!!!!","keywords":[],"urls":[],"user_verified":false,"class":"Infractions","date":"2016-04-25T03:06:03Z","lang":"en","retweets":8,"city":"Atlanta"},{"tags":["speeding"],"id":724605565066989568,"text":"Listening to Don't Hurt Yourself while speeding is EVERYTHING","keywords":[],"urls":[],"user_verified":false,"class":"Infractions","date":"2016-04-25T02:26:43Z","lang":"en","retweets":0,"city":"Atlanta"},{"tags":["speeding"],"id":724602049283940353,"text":"Panthers RB Cameron Artis-Payne arrested for speeding clocked driving 102 mph in a 65 mph zone","keywords":[],"urls":[],"user_verified":false,"class":"Infractions","date":"2016-04-25T02:12:45Z","lang":"en","retweets":0,"city":"Atlanta"},{"tags":["speeding"],"id":724533163800858624,"text":"Watch a stuntman do a terrifying blind backflip over a speeding Formula E car https://t.co/hERyfyzHwb","keywords":[],"urls":["http://bit.ly/1SUOiPo"],"user_verified":false,"class":"Infractions","predicted_location":"","date":"2016-04-25T09:39:02Z","lang":"en","retweets":0,"city":"Atlanta"},{"tags":["speeding"],"id":724460510608003072,"text":"@_zymera yes speeding on me quick fast in. A hurry !","keywords":[],"urls":[],"user_verified":false,"class":"Infractions","date":"2016-04-25T04:50:20Z","lang":"en","retweets":0,"city":"Atlanta"},{"tags":["speeding"],"id":724454017078800384,"text":"RT @The_Steezo: I swear speeding on the highway has to be one of the top ten greatest feelings","keywords":[],"urls":[],"user_verified":false,"class":"Infractions","date":"2016-04-25T04:24:32Z","lang":"en","retweets":1,"city":"Atlanta"},{"tags":["speeding"],"id":724453950326476800,"text":"I swear speeding on the highway has to be one of the top ten greatest feelings","keywords":[],"urls":[],"user_verified":false,"class":"Infractions","date":"2016-04-25T04:24:16Z","lang":"en","retweets":1,"city":"Atlanta"},{"tags":["hit","speeding","ticket"],"id":724425594587459584,"text":"Calm the hell down yall. He got a speeding ticket! Shit happens to ppl all the time. #letcapdrive","keywords":["letcapdrive"],"urls":[],"user_verified":false,"class":"Assault","date":"2016-04-25T02:31:35Z","lang":"en","retweets":0,"city":"Atlanta"},{"tags":["speeding"],"id":724422390009106432,"text":"@playboydolans SPEEDING ON THE HIGHWAY","keywords":[],"urls":[],"user_verified":false,"class":"Infractions","date":"2016-04-25T02:18:51Z","lang":"en","retweets":0,"city":"Atlanta"},{"tags":["running"],"id":724405751041560577,"text":"Report: Carolina Panthers running back arrested https://t.co/oTv1ESzoGB","keywords":[],"urls":["http://fb.me/12B4WoFTO"],"user_verified":false,"class":"Infractions","date":"2016-04-25T01:12:44Z","lang":"en","retweets":0,"city":"Atlanta"},{"tags":["speeding","ticket"],"id":724391595915751424,"text":"How to get out of a speeding ticket, excuse #4. \n\"Well, when I reached down to pick up my bag of crack, my gun... https://t.co/nrVWrsD1Iz","keywords":[],"urls":["http://fb.me/4uzr8DxQx"],"user_verified":false,"class":"Infractions","date":"2016-04-25T12:16:29Z","lang":"en","retweets":0,"city":"Atlanta"},{"tags":["speeding","ticket"],"id":724369060041875456,"text":"Is it even a road trip if you didn't get a speeding ticket?","keywords":[],"urls":[],"user_verified":false,"class":"Infractions","date":"2016-04-24T10:46:56Z","lang":"en","retweets":0,"city":"Atlanta"},{"tags":["speeding","ticket"],"id":724355935779446785,"text":"I need to start saving for this fat speeding ticket I got 🙃","keywords":[],"urls":[],"user_verified":false,"class":"Infractions","date":"2016-04-24T09:54:47Z","lang":"en","retweets":0,"city":"Atlanta"},{"tags":["littering"],"id":724350499286216705,"text":"Amazing that with Rahal's front wing littering the @BarberMotorPark track there is no caution. #IndyCar #HIGPA","keywords":["IndyCar","HIGPA"],"urls":[],"user_verified":false,"class":"Infractions","date":"2016-04-24T09:33:11Z","lang":"en","retweets":0,"city":"Atlanta"},{"tags":["speeding","ticket"],"id":724342130324414464,"text":"First offender speeding ticket $261. FUCK DEKALB COUNTY🖕🏾😤","keywords":[],"urls":[],"user_verified":false,"class":"Infractions","date":"2016-04-24T08:59:56Z","lang":"en","retweets":0,"city":"Atlanta"},{"tags":[],"id":724306622009475076,"text":"Landing A U-2 Is A HARD Job And Requires Something Extra https://t.co/yUIcKQJx96","keywords":[],"urls":["http://worldwarwings.com/u-2-bomber-gets-pulled-over-for-speeding?a=mk&var=pinups-u2-pullover"],"user_verified":false,"class":"Unclassified","date":"2016-04-24T06:38:50Z","lang":"en","retweets":0,"city":"Atlanta"},{"tags":["speeding"],"id":724299380786892800,"text":"A woman driving 142mph got caught speeding... WITH two kinds in the backseat.. Oh the humanity where did it go wrong..?","keywords":[],"urls":[],"user_verified":false,"class":"Infractions","date":"2016-04-24T06:10:03Z","lang":"en","retweets":0,"city":"Atlanta"},{"tags":["speeding"],"id":724296137641988096,"text":"Just got blue lighted for speeding, not pulled over though. Jeep still trucking on with the clean record.","keywords":[],"urls":[],"user_verified":false,"class":"Infractions","date":"2016-04-24T05:57:10Z","lang":"en","retweets":0,"city":"Atlanta"},{"tags":[],"id":724283044425793536,"text":"I hate you loud talking heifers who always come in the nail shop disturbing the peace like some owe you something","keywords":[],"urls":[],"user_verified":false,"class":"Unclassified","date":"2016-04-24T05:05:08Z","lang":"en","retweets":0,"city":"Atlanta"},{"tags":["littering"],"id":724244143455641600,"text":"RT @TheTyraTales: littering is so tacky.  https://t.co/we0Nseaq5y","keywords":[],"urls":["https://twitter.com/taidyes/status/723561590142828544"],"user_verified":false,"class":"Infractions","date":"2016-04-24T02:30:34Z","lang":"en","retweets":3,"city":"Atlanta"},{"tags":["speeding","ticket"],"id":724240572412780544,"text":"Good morning, I just got a speeding ticket and a seatbelt ticket. Hope your morning is going GREAT!","keywords":[],"urls":[],"user_verified":false,"class":"Infractions","date":"2016-04-24T02:16:22Z","lang":"en","retweets":0,"city":"Atlanta"},{"tags":["speeding"],"id":724225387811770369,"text":"When the state boys pull u for speeding but your driving record is spotless so you get a warning sheeeesh GM world","keywords":[],"urls":[],"user_verified":false,"class":"Infractions","date":"2016-04-24T01:16:02Z","lang":"en","retweets":0,"city":"Atlanta"},{"tags":["jaywalking"],"id":724224531968057344,"text":"the One &Only who's Jaywalking who makes his own #workhard get his success & to be boss of welknown music label #30thAomgBossBday #HappyJday","keywords":["workhard","30thAomgBossBday","HappyJday"],"urls":[],"user_verified":false,"class":"Infractions","date":"2016-04-24T01:12:38Z","lang":"en","retweets":0,"city":"Atlanta"},{"tags":["speeding"],"id":724108715381678081,"text":"Walking On Cars - Speeding Cars https://t.co/YJ97E60iEO #nowplaying #listenlive","keywords":["nowplaying","listenlive"],"urls":["http://rdo.to/WBMR"],"user_verified":false,"class":"Infractions","date":"2016-04-24T05:32:25Z","lang":"en","retweets":0,"city":"Atlanta"},{"tags":["speeding"],"id":724056155203461120,"text":"<==== only got pulled over once for speeding  https://t.co/UpStCERwXF","keywords":[],"urls":["https://twitter.com/logo_ukno/status/724055856308981761"],"user_verified":false,"class":"Infractions","date":"2016-04-24T02:03:34Z","lang":"en","retweets":0,"city":"Atlanta"},{"tags":["speeding"],"id":724046543121178624,"text":"My five month son just be crawling everywhere. And be speeding 😂😂he be putting the burners on my ass 🌚🌚😫","keywords":[],"urls":[],"user_verified":false,"class":"Infractions","date":"2016-04-24T01:25:22Z","lang":"en","retweets":0,"city":"Atlanta"},{"tags":["speeding"],"id":724045449519202304,"text":"us speeding to Abrielle's house cause she got HBO https://t.co/EyHFKmWWJx","keywords":[],"urls":[],"user_verified":false,"class":"Infractions","date":"2016-04-24T01:21:01Z","lang":"en","retweets":0,"city":"Atlanta"},{"tags":["speeding"],"id":724018386653593601,"text":"RT @QueenTahtiana: When I drive high I feel like I'm speeding but I'm actually doing speed limit","keywords":[],"urls":[],"user_verified":false,"class":"Infractions","date":"2016-04-23T11:33:29Z","lang":"en","retweets":11,"city":"Atlanta"},{"tags":["speeding","ticket"],"id":724018365824684032,"text":"@ShanBreezyy I know you gonna be speeding home, probably catch a ticket lmao","keywords":[],"urls":[],"user_verified":false,"class":"Infractions","date":"2016-04-23T11:33:24Z","lang":"en","retweets":0,"city":"Atlanta"},{"tags":["speeding","ticket"],"id":724014806139727872,"text":"RT @madscape: And I'm not talking just normal speeding tickets dude, excess of 80 miles an hour what's wrong with you man https://t.co/Yiik\u2026","keywords":[],"urls":["https://twitter.com/RickCanton/status/724012958054010880"],"user_verified":false,"class":"Infractions","date":"2016-04-23T11:19:15Z","lang":"en","retweets":2,"city":"Atlanta"},{"tags":["speeding","ticket"],"id":724013748353138688,"text":"And I'm not talking just normal speeding tickets dude, excess of 80 miles an hour what's wrong with you man https://t.co/YiikXCg6BY","keywords":[],"urls":["https://twitter.com/RickCanton/status/724012958054010880"],"user_verified":false,"class":"Infractions","date":"2016-04-23T11:15:03Z","lang":"en","retweets":2,"city":"Atlanta"},{"tags":["speeding","ticket"],"id":724013529767002113,"text":"How can I be jealous of an ex-cop that has more speeding tickets all over this country than anybody I've ever seen https://t.co/YiikXCg6BY","keywords":[],"urls":["https://twitter.com/RickCanton/status/724012958054010880"],"user_verified":false,"class":"Infractions","date":"2016-04-23T11:14:11Z","lang":"en","retweets":0,"city":"Atlanta"},{"tags":["speeding"],"id":723996542999375873,"text":"Mortgage closing times are speeding up https://t.co/wbgcN1Qnw0 https://t.co/cr4UIvn4HS","keywords":[],"urls":["http://realtormag.realtor.org/daily-news/2016/04/22/closing-times-are-speeding-up"],"user_verified":false,"class":"Infractions","date":"2016-04-23T10:06:41Z","lang":"en","retweets":0,"city":"Atlanta"},{"tags":["speeding"],"id":723993879494680576,"text":"RT @paul_dewaard: So, I just saw a deer jump right over a speeding Smartcar from Jimmy John's BBQ.  I wonder if I just witnessed an unsucce\u2026","keywords":[],"urls":[],"user_verified":false,"class":"Infractions","date":"2016-04-23T09:56:06Z","lang":"en","retweets":6,"city":"Atlanta"},{"tags":["speeding"],"id":723986028537761793,"text":"Speeding Home to watch the Heat game 😩","keywords":[],"urls":[],"user_verified":false,"class":"Infractions","date":"2016-04-23T09:24:54Z","lang":"en","retweets":0,"city":"Atlanta"},{"tags":["hit","speeding"],"id":723933103136354305,"text":"No dick riding shit. @KidCudi really has some in loyal ass fans. All of Speeding bullet is still stuck in my head.","keywords":[],"urls":[],"user_verified":false,"class":"Assault","date":"2016-04-23T05:54:36Z","lang":"en","retweets":0,"city":"Atlanta"},{"tags":["speeding","ticket","running"],"id":723931758329225216,"text":"I got to get a sports car again so I can start back outrunning 12. Wouldn't be getting all these speeding tickets that way.","keywords":[],"urls":[],"user_verified":false,"class":"Infractions","date":"2016-04-23T05:49:15Z","lang":"en","retweets":0,"city":"Atlanta"},{"tags":["speeding","ticket"],"id":723916340826804231,"text":"How fast do your kids drive? They're 3x more likely to get a speeding ticket!","keywords":[],"urls":[],"user_verified":false,"class":"Infractions","date":"2016-04-23T04:48:00Z","lang":"en","retweets":0,"city":"Atlanta"},{"tags":["speeding"],"id":723900267155079168,"text":"Somebody tell Marquis young swole ass to stop coming thru da neighborhood speeding lol 😂😂😂","keywords":[],"urls":[],"user_verified":false,"class":"Infractions","date":"2016-04-23T03:44:07Z","lang":"en","retweets":0,"city":"Atlanta"},{"tags":["hit","speeding"],"id":723891055737856000,"text":"I don't wanna hear SHIT about me speeding!😂😂","keywords":[],"urls":[],"user_verified":false,"class":"Assault","date":"2016-04-23T03:07:31Z","lang":"en","retweets":0,"city":"Atlanta"},{"tags":["hit","speeding","ticket"],"id":723877912152313856,"text":"Got my first speeding ticket to add to the shitty week I've had 🤗","keywords":[],"urls":[],"user_verified":false,"class":"Assault","date":"2016-04-23T02:15:17Z","lang":"en","retweets":0,"city":"Atlanta"},{"tags":["speeding","ticket"],"id":723870431938285568,"text":"I liked a @YouTube video https://t.co/oW6kXsDgqM The Angry Birds Movie - \"Speeding Ticket\" Clip","keywords":[],"urls":["http://youtu.be/W3ncvtDKUd4?a"],"user_verified":false,"class":"Infractions","date":"2016-04-23T01:45:34Z","lang":"en","retweets":0,"city":"Atlanta"},{"tags":["speeding"],"id":723865122796638208,"text":"Walking On Cars - Speeding Cars https://t.co/YJ97E60iEO #nowplaying #listenlive","keywords":["nowplaying","listenlive"],"urls":["http://rdo.to/WBMR"],"user_verified":false,"class":"Infractions","date":"2016-04-23T01:24:28Z","lang":"en","retweets":0,"city":"Atlanta"},{"tags":["speeding","ticket"],"id":723860316937945088,"text":"Once got a speeding ticket that cost me ~$100. The next day I got a letter from the state that said I overpaid my taxes, w/ a ~$100 check.","keywords":[],"urls":[],"user_verified":false,"class":"Infractions","date":"2016-04-23T01:05:22Z","lang":"en","retweets":0,"city":"Atlanta"},{"tags":["jaywalking"],"id":723857772056551424,"text":"I wouldn't remember the huge country concert in the stadium is today if it weren't for the high number of people jaywalking in cowboy boots.","keywords":[],"urls":[],"user_verified":false,"class":"Infractions","date":"2016-04-23T12:55:16Z","lang":"en","retweets":0,"city":"Atlanta"},{"tags":["jaywalking"],"id":723846170737520640,"text":"@nahPmaL Margaret Mitchell died jaywalking. I may go to her cemetery today to a tour of trees at 1 #BuddySystem. https://t.co/uevce1acYL","keywords":["BuddySystem"],"urls":["http://www.history.com/topics/holidays/womens-history-month/videos/aint-i-a-woman"],"user_verified":false,"class":"Infractions","date":"2016-04-23T12:09:10Z","lang":"en","retweets":0,"city":"Atlanta"},{"tags":["speeding"],"id":723834778907205633,"text":"@queenceeeee_ freak accident by someone who was speeding, not drunk. So there is a whole difference.","keywords":[],"urls":[],"user_verified":false,"class":"Infractions","date":"2016-04-23T11:23:54Z","lang":"en","retweets":0,"city":"Atlanta"},{"tags":["hit","speeding"],"id":723776511929544704,"text":"If she ever needed me I came speeding believe me 😊💯 ain't shit changed 💯","keywords":[],"urls":[],"user_verified":false,"class":"Assault","date":"2016-04-23T07:32:22Z","lang":"en","retweets":0,"city":"Atlanta"},{"tags":["speeding"],"id":723756254108233728,"text":"I liked a @YouTube video https://t.co/upxcxKyX0C IN-CAR DirtLateModel compilation \"FLATOUT\" Demon Speeding","keywords":[],"urls":["http://youtu.be/-osPZfAMHtA?a"],"user_verified":false,"class":"Infractions","date":"2016-04-23T06:11:52Z","lang":"en","retweets":0,"city":"Atlanta"},{"tags":["speeding"],"id":723733671715454978,"text":"I just published \u201cSpeeding up Rails + SCSS\u201d https://t.co/aiE909gpyQ","keywords":[],"urls":["https://medium.com/@justinlicata/speeding-up-rails-scss-c97f0af38707#.h9tkv8792"],"user_verified":false,"class":"Infractions","date":"2016-04-23T04:42:08Z","lang":"en","retweets":0,"city":"Atlanta"},{"tags":["speeding"],"id":723717698073534464,"text":"His ass be speeding in this damn car. After party tho 😈","keywords":[],"urls":[],"user_verified":false,"class":"Infractions","date":"2016-04-23T03:38:39Z","lang":"en","retweets":0,"city":"Atlanta"},{"tags":["speeding"],"id":723705047557660672,"text":"My heavy ass foot 😩 I always get caught speeding 😒","keywords":[],"urls":[],"user_verified":false,"class":"Infractions","date":"2016-04-23T02:48:23Z","lang":"en","retweets":0,"city":"Atlanta"},{"tags":["speeding"],"id":723703634370936833,"text":"RT @wavychaos: this speeding care is so nice https://t.co/c56ZxDwaCa","keywords":[],"urls":["https://twitter.com/gabbylavezzoli/status/723671210815557632"],"user_verified":false,"class":"Infractions","date":"2016-04-23T02:42:46Z","lang":"en","retweets":1,"city":"Atlanta"},{"tags":["speeding"],"id":723702735141396480,"text":"this speeding care is so nice https://t.co/c56ZxDwaCa","keywords":[],"urls":["https://twitter.com/gabbylavezzoli/status/723671210815557632"],"user_verified":false,"class":"Infractions","date":"2016-04-23T02:39:12Z","lang":"en","retweets":1,"city":"Atlanta"},{"tags":["speeding"],"id":723694992833810432,"text":"Police say why are you speeding Mr.Terry 🤔 lol I told his asz \"because I didn't see you\"","keywords":[],"urls":[],"user_verified":false,"class":"Infractions","date":"2016-04-23T02:08:26Z","lang":"en","retweets":0,"city":"Atlanta"},{"tags":["speeding"],"id":723679838775705601,"text":"Walking On Cars - Speeding Cars https://t.co/YJ97E60iEO #nowplaying #listenlive","keywords":["nowplaying","listenlive"],"urls":["http://rdo.to/WBMR"],"user_verified":false,"class":"Infractions","date":"2016-04-23T01:08:13Z","lang":"en","retweets":0,"city":"Atlanta"},{"tags":["speeding"],"id":723665166928322561,"text":"Mfs be speeding up like I won't  cut that ass off 💅🏻","keywords":[],"urls":[],"user_verified":false,"class":"Infractions","date":"2016-04-23T12:09:55Z","lang":"en","retweets":0,"city":"Atlanta"}]