[{"id":720743047588376576,"text":"Walking a mile with @scstsm to raise awareness for sexual assault! Thank you for letting us be\u2026 https://t.co/oSV6E0Is7E","keywords":[],"source":"Twitter","location":"Los Angeles","urls":["https://www.instagram.com/p/BEMp2srIOjN/"],"date":"2016-04-14T10:38:27Z","lang":"en"},{"id":720559665810161664,"text":"Kobe would have more accolades without the rape case, shouldn't be the reason for him being slighted but it was","keywords":[],"source":"Twitter","location":"Los Angeles","urls":[],"date":"2016-04-14T10:29:46Z","lang":"en"},{"id":720065512382799872,"text":"\"Um hey so Murder in the City changed my life and, um, y'all are awesome.\" You know it's awkward\u2026 https://t.co/dGuGIJ5HxK","keywords":[],"source":"Twitter","location":"Los Angeles","urls":["https://www.instagram.com/p/BEH1v3-OgPp/"],"date":"2016-04-13T01:46:10Z","lang":"en"},{"id":718962031366434816,"text":"Proud Daughters moment. \nDaddy is Guest of Honor at the 2nd Assault Amphibian Battalion  Gator\u2026 https://t.co/1JT8BfvAaw","keywords":[],"source":"Twitter","location":"Los Angeles","urls":["https://www.instagram.com/p/BD__8TunQXO/"],"date":"2016-04-10T12:41:20Z","lang":"en"}]