[{"tags":["robbery"],"id":723296543508328451,"text":"Ex-USC Tight End -- 6 Years In Prison ... For Violent Robbery Spree: The former USC football player accused of\u2026 https://t.co/2Z5tb9o9Ad","keywords":[],"urls":["http://dlvr.it/L6kJ4Y"],"user_verified":false,"class":"Robbery","date":"2016-04-21T11:45:08Z","lang":"en","retweets":0,"city":"Chicago"},{"tags":["mugging "],"id":723296502148390912,"text":"RT @NoviNovak: I started carrying a knife after an attempted mugging a few years ago. Since then, my mugging attempts have been a lot more\u2026","keywords":[],"urls":[],"user_verified":false,"class":"Robbery","date":"2016-04-21T11:44:58Z","lang":"en","retweets":64,"city":"Chicago"},{"tags":["robbery"],"id":723294688262819841,"text":"Ex-USC Tight End -- 6 Years In Prison ... For Violent Robbery Spree https://t.co/zxCirTYlNd","keywords":[],"urls":["http://bit.ly/1VJKXJi"],"user_verified":false,"class":"Robbery","date":"2016-04-21T11:37:46Z","lang":"en","retweets":0,"city":"Chicago"},{"tags":["kill","robbery"],"id":723293606610644993,"text":"he believes that Mike Brown was \"high on marijuana and had just committed a robbery and the officer that killed him is no criminal\"","keywords":[],"urls":[],"user_verified":false,"class":"Murder","date":"2016-04-21T11:33:28Z","lang":"en","retweets":0,"city":"Chicago"},{"tags":["robbery"],"id":723293000646963200,"text":"K-INDEMAND NEWS Ex-USC Tight End -- 6 Years In Prison ... For Violent Robbery Spree https://t.co/i8YEzHg1qP","keywords":[],"urls":["http://ow.ly/8JEyha"],"user_verified":false,"class":"Robbery","date":"2016-04-21T11:31:04Z","lang":"en","retweets":0,"city":"Chicago"},{"tags":["robbery"],"id":723291031303688192,"text":"Robbery thwarted by cyclist's smooth take down: \n\nA Good Samaritan was able to stop a robbery in pr... https://t.co/wrvQgJC7R6 #seo #IT","keywords":["seo","IT"],"urls":["http://on.mash.to/2128GUN"],"user_verified":false,"class":"Robbery","date":"2016-04-21T11:23:14Z","lang":"en","retweets":0,"city":"Chicago"},{"tags":["robbery"],"id":723291014643867648,"text":"Robbery thwarted by cyclist's smooth take down: \n\nA Good Samaritan was able to stop a robbery in progress th... https://t.co/pHFyPLh0ey","keywords":[],"urls":["http://on.mash.to/1Vo5T8R"],"user_verified":false,"class":"Robbery","date":"2016-04-21T11:23:10Z","lang":"en","retweets":0,"city":"Chicago"},{"tags":["robbery"],"id":723291013419147264,"text":"#Robbery thwarted by cyclist's smooth take down https://t.co/knNLEe1SYQ","keywords":["Robbery"],"urls":["http://mashable.com/2016/04/21/cyclist-stops-robbery/"],"user_verified":false,"class":"Robbery","date":"2016-04-21T11:23:10Z","lang":"en","retweets":0,"city":"Chicago"},{"tags":["robbery"],"id":723290731989729280,"text":"Robbery thwarted by cyclist's smooth take down: \n\nA Good Samaritan was able to stop a robbery in progress th... https://t.co/kRCgOkzdjN","keywords":[],"urls":["http://on.mash.to/1Vo5T8R"],"user_verified":false,"class":"Robbery","date":"2016-04-21T11:22:03Z","lang":"en","retweets":0,"city":"Chicago"},{"tags":["robbery"],"id":723290723479511040,"text":"Robbery thwarted by cyclist's smooth take down: \n\nA Good Samaritan was able to stop a robbery in progress th... https://t.co/IusnvDWXUZ","keywords":[],"urls":["http://on.mash.to/1Vo5T8R"],"user_verified":false,"class":"Robbery","date":"2016-04-21T11:22:01Z","lang":"en","retweets":0,"city":"Chicago"},{"tags":["robbery"],"id":723290718605742080,"text":"Robbery thwarted by cyclist's smooth take down: \n\nA Good Samaritan was able to stop a robbery in progress th... https://t.co/tCapAMdGzB","keywords":[],"urls":["http://on.mash.to/1Vo5T8R"],"user_verified":false,"class":"Robbery","date":"2016-04-21T11:22:00Z","lang":"en","retweets":0,"city":"Chicago"},{"tags":["robbery"],"id":723289513393577984,"text":"Anything more than 1.50 for swishers is robbery. Fuck I hate the north side","keywords":[],"urls":[],"user_verified":false,"class":"Robbery","predicted_location":"","date":"2016-04-21T11:17:12Z","lang":"en","retweets":0,"city":"Chicago"},{"tags":["robbery"],"id":723288801381126145,"text":"Suspect identified in #Rockford bank robbery https://t.co/lJ5ZKFdjPr https://t.co/9YmjiGQRlL","keywords":["Rockford"],"urls":["http://ow.ly/4mXLeS"],"user_verified":false,"class":"Robbery","date":"2016-04-21T11:14:22Z","lang":"en","retweets":1,"city":"Chicago"},{"tags":["robbery"],"id":723286006800117761,"text":"UPDATE: Suspect Identified in Rockford Bank Robbery https://t.co/QSsT1tyo0q","keywords":[],"urls":["http://bit.ly/1SeJk3Y"],"user_verified":false,"class":"Robbery","date":"2016-04-21T11:03:16Z","lang":"en","retweets":0,"city":"Chicago"},{"tags":["robbery"],"id":723279687166902272,"text":"RT @WestAllisPD: ** Assistance Needed - Armed Robbery **\n\nWe are trying to identify the person in the attached photos in regards... https:/\u2026","keywords":[],"urls":["http://fb.me/4UQh9EdPC"],"user_verified":false,"class":"Robbery","date":"2016-04-21T10:38:09Z","lang":"en","retweets":1,"city":"Chicago"},{"tags":["robbery"],"id":723275236435746816,"text":"This bank robbery actually happened in Detroit - Shouldn't laugh, but it's hard not to. - https://t.co/D7U0KDqBjp","keywords":[],"urls":["http://fb.me/7YEbKIzjn"],"user_verified":false,"class":"Robbery","date":"2016-04-21T10:20:28Z","lang":"en","retweets":0,"city":"Chicago"},{"tags":["robbery"],"id":723272347969441793,"text":"** Assistance Needed - Armed Robbery **\n\nWe are trying to identify the person in the attached photos in regards... https://t.co/Wxwc53EKXu","keywords":[],"urls":["http://fb.me/4UQh9EdPC"],"user_verified":false,"class":"Robbery","date":"2016-04-21T10:09:00Z","lang":"en","retweets":1,"city":"Chicago"},{"tags":["robbery","fire"],"id":723247877150105600,"text":"Shot fired in Milwaukee bank during robbery, police say https://t.co/lOxA71GxUK","keywords":[],"urls":["http://fb.me/tHBXhywF"],"user_verified":false,"class":"Robbery","date":"2016-04-21T08:31:45Z","lang":"en","retweets":0,"city":"Chicago"},{"tags":["robbery"],"id":723246147297509376,"text":"Man charged with felony robbery after pouring $1.49 worth of McDonald\u2019s soda into water cup https://t.co/VP8ivaq4ef","keywords":[],"urls":["http://www.rawstory.com/2016/04/man-charged-with-felony-robbery-after-pouring-1-49-worth-of-mcdonalds-soda-into-water-cup/#.Vxk3E4vISMk.twitter"],"user_verified":false,"class":"Robbery","date":"2016-04-21T08:24:53Z","lang":"en","retweets":0,"city":"Chicago"},{"tags":["robbery"],"id":723241456303923200,"text":"#rockfordlink Rockford Police investigating armed robbery to Chase\u2026 https://t.co/9wJOqZLpDq https://t.co/OnNvjtNwAV https://t.co/PHoMfvjG5c","keywords":["rockfordlink"],"urls":["http://dlvr.it/L6fvfC","http://www.rockfordlink.com"],"user_verified":false,"class":"Robbery","date":"2016-04-21T08:06:15Z","lang":"en","retweets":0,"city":"Chicago"},{"tags":["robbery"],"id":723241183590240256,"text":"#rockford_il Rockford Police investigating armed robbery to Chase Bank -\u2026 https://t.co/Vcrj0sCF0N #rockfordlink https://t.co/9CBd8RprPs","keywords":["rockford_il","rockfordlink"],"urls":["http://dlvr.it/L6fvWY"],"user_verified":false,"class":"Robbery","date":"2016-04-21T08:05:09Z","lang":"en","retweets":0,"city":"Chicago"},{"tags":[],"id":723230731154165760,"text":"Remember this next time you ask for a \"water cup\"\nhttps://t.co/gUooEACaYc","keywords":[],"urls":["http://www.foxnews.com/us/2016/04/20/mcdonalds-customer-accused-putting-soda-in-water-cup-charged-with-robbery.html"],"user_verified":false,"class":"Unclassified","date":"2016-04-21T07:23:37Z","lang":"en","retweets":0,"city":"Chicago"},{"tags":["robbery"],"id":723229167286816768,"text":"18 year old male charged with a felony robbery for putting water in a soda cup at McDonald's ... That's so Wack....","keywords":[],"urls":[],"user_verified":false,"class":"Robbery","date":"2016-04-21T07:17:25Z","lang":"en","retweets":0,"city":"Chicago"},{"tags":["robbery"],"id":723228018139914240,"text":"Taxation is robbery based on monopoly of weapons","keywords":[],"urls":[],"user_verified":false,"class":"Robbery","date":"2016-04-21T07:12:51Z","lang":"en","retweets":0,"city":"Chicago"},{"tags":["robbery"],"id":723217108029435904,"text":"@NickQUINNING @JonobRatchet103 the headline is missing the fact that he was bumping chief keef in his headphones during the robbery","keywords":[],"urls":[],"user_verified":false,"class":"Robbery","date":"2016-04-21T06:29:29Z","lang":"en","retweets":0,"city":"Chicago"},{"tags":["robbery","fire"],"id":723211358917918720,"text":"Shot fired in Milwaukee bank during robbery, police say  #Wisconsin","keywords":["Wisconsin"],"urls":[],"user_verified":false,"class":"Robbery","date":"2016-04-21T06:06:39Z","lang":"en","retweets":0,"city":"Chicago"},{"tags":["robbery"],"id":723206193188114432,"text":"Love you forever. A cruel robbery has occurred. https://t.co/xKhWagO1xS","keywords":[],"urls":["https://www.instagram.com/p/BEeJ9sZQ6bH/"],"user_verified":false,"class":"Robbery","date":"2016-04-21T05:46:07Z","lang":"en","retweets":0,"city":"Chicago"},{"tags":["shoplifting","shoplifting"],"id":723205456789905408,"text":"RT @KevinPluchar: Louisiana man may face life for shoplifting Snickers bars https://t.co/SIpnlf8ABJ via @HuffPostCrime #LeydenLaw","keywords":["LeydenLaw"],"urls":["http://www.huffingtonpost.com/entry/louisiana-snickers-habitual-offender_us_5711291fe4b0060ccda32cd5"],"user_verified":false,"class":"Robbery","date":"2016-04-21T05:43:12Z","lang":"en","retweets":1,"city":"Chicago"},{"tags":["robbery"],"id":723205284651503616,"text":"RT @fox32news: REALLY?? @McDonalds customer charged with robbery for putting soda in his water cup https://t.co/gkTVdL3BAi https://t.co/ssk\u2026","keywords":[],"urls":["http://bit.ly/1NC5NlY"],"user_verified":false,"class":"Robbery","date":"2016-04-21T05:42:31Z","lang":"en","retweets":18,"city":"Chicago"},{"tags":["mugging "],"id":723203808092934144,"text":"RT @sulej_geo: Basically mugging yourself off if you get involved with someone who's still involved with their ex 😴","keywords":[],"urls":[],"user_verified":false,"class":"Robbery","date":"2016-04-21T05:36:38Z","lang":"en","retweets":11,"city":"Chicago"},{"tags":["robbery"],"id":723201851571769344,"text":"RT @fox6now: Police seek two suspects after armed robbery at North Shore Bank near 92nd & Oklahoma: https://t.co/UncBwKseUE https://t.co/NT\u2026","keywords":[],"urls":["http://via.fox6now.com/4sbDC"],"user_verified":false,"class":"Robbery","predicted_location":"","date":"2016-04-21T05:28:52Z","lang":"en","retweets":1,"city":"Chicago"},{"tags":["robbery"],"id":723199274109030401,"text":"Police seek two suspects after armed robbery at North Shore Bank near 92nd & Oklahoma: https://t.co/UncBwKseUE https://t.co/NT3N2umFiC","keywords":[],"urls":["http://via.fox6now.com/4sbDC"],"user_verified":true,"class":"Robbery","predicted_location":"","date":"2016-04-21T05:18:37Z","lang":"en","retweets":1,"city":"Chicago"},{"tags":["robbery"],"id":723197554725294082,"text":"\"McDonald's customer accused of putting soda in water cup charged with robbery\"  https://t.co/P1CT7plhbo","keywords":[],"urls":["http://www.foxla.com/news/127622711-story"],"user_verified":false,"class":"Robbery","date":"2016-04-21T05:11:48Z","lang":"en","retweets":0,"city":"Chicago"},{"tags":["robbery"],"id":723194376311033857,"text":"#news High street agent helps foil armed robbery https://t.co/UGjtcAgabU","keywords":["news"],"urls":["http://j.mp/1SdRPw6"],"user_verified":false,"class":"Robbery","date":"2016-04-21T04:59:10Z","lang":"en","retweets":0,"city":"Chicago"},{"tags":["robbery"],"id":723193528365371393,"text":"#news High street agent helps foil armed robbery https://t.co/3HYKCLvvQ7","keywords":["news"],"urls":["http://j.mp/244F6Qf"],"user_verified":false,"class":"Robbery","date":"2016-04-21T04:55:48Z","lang":"en","retweets":0,"city":"Chicago"},{"tags":["robbery"],"id":723191643612975104,"text":"I'M DYING OMG 💀💀💀\"McDonald's customer accused of putting soda in water cup charged with robbery\" https://t.co/jID4WIchwg","keywords":[],"urls":["http://www.foxla.com/news/127622711-story"],"user_verified":false,"class":"Robbery","date":"2016-04-21T04:48:18Z","lang":"en","retweets":0,"city":"Chicago"},{"tags":["mugging "],"id":723182772689444864,"text":"She really mugging thinking I'm suppose to be scared of her. . #mydaughter #myworld https://t.co/MYfzySrWNM","keywords":["mydaughter","myworld"],"urls":[],"user_verified":false,"class":"Robbery","date":"2016-04-21T04:13:03Z","lang":"en","retweets":1,"city":"Chicago"},{"tags":["robbery"],"id":723181609537658880,"text":"RT @fox32news: REALLY?? @McDonalds customer charged with robbery for putting soda in his water cup https://t.co/gkTVdL3BAi https://t.co/ssk\u2026","keywords":[],"urls":["http://bit.ly/1NC5NlY"],"user_verified":false,"class":"Robbery","date":"2016-04-21T04:08:26Z","lang":"en","retweets":18,"city":"Chicago"},{"tags":["robbery"],"id":723181167445463040,"text":"RT @Chicagowise: 10:34 am: male passenger holding a male robbery suspect @ Jackson CTA Red Line subway station, 230 S State St. Plainclothe\u2026","keywords":[],"urls":[],"user_verified":false,"class":"Robbery","predicted_location":"","date":"2016-04-21T04:06:41Z","lang":"en","retweets":1,"city":"Chicago"},{"tags":["robbery"],"id":723174650956656641,"text":"10:34 am: male passenger holding a male robbery suspect @ Jackson CTA Red Line subway station, 230 S State St. Plainclothes cops responding.","keywords":[],"urls":[],"user_verified":false,"class":"Robbery","predicted_location":"","date":"2016-04-21T03:40:47Z","lang":"en","retweets":1,"city":"Chicago"},{"tags":["robbery"],"id":723174120251383808,"text":"RT @TrackCityChick: The whole world should be charged with robbery then. I don't know anyone who doesn't do this 💀😂 https://t.co/kv9PPbEHSR","keywords":[],"urls":["https://twitter.com/fox5dc/status/722938311870849024"],"user_verified":false,"class":"Robbery","date":"2016-04-21T03:38:40Z","lang":"en","retweets":1,"city":"Chicago"},{"tags":["robbery"],"id":723173641463066627,"text":"McDonald's customer accused of putting soda in water cup charged with robbery https://t.co/PuLmsw0xOM @MVPisCOOLER @JayMart2k","keywords":[],"urls":["http://www.foxla.com/news/127622711-story"],"user_verified":false,"class":"Robbery","date":"2016-04-21T03:36:46Z","lang":"en","retweets":0,"city":"Chicago"},{"tags":["shoplifting","shoplifting"],"id":723172999256530944,"text":"As of today I quit shoplifting. Karma is everywhere","keywords":[],"urls":[],"user_verified":false,"class":"Robbery","date":"2016-04-21T03:34:13Z","lang":"en","retweets":0,"city":"Chicago"},{"tags":["robbery","attack"],"id":723166117863165952,"text":"Hurley says this area has robbery, violent attack, etc. \"every other day.\" If 7-Eleven doesn't know that \"they need to know that, but they..","keywords":[],"urls":[],"user_verified":true,"class":"Assault","date":"2016-04-21T03:06:52Z","lang":"en","retweets":0,"city":"Chicago"},{"tags":["robbery"],"id":723158836501045248,"text":"A man who put McDonald's soda in a water cup is charged with robbery https://t.co/UvcICdvYHn via @MailOnline","keywords":[],"urls":["http://dailym.ai/1Tl39p4"],"user_verified":false,"class":"Robbery","date":"2016-04-21T02:37:56Z","lang":"en","retweets":0,"city":"Chicago"},{"tags":["robbery"],"id":723157142535057408,"text":"@roadbreakersapp: Police investigating armed robbery at Perry County truck stop - https://t.co/RlMXX66RaX #GoogleAlerts","keywords":["GoogleAlerts"],"urls":["http://bit.ly/23KGdYS"],"user_verified":false,"class":"Robbery","date":"2016-04-21T02:31:13Z","lang":"en","retweets":0,"city":"Chicago"},{"tags":["robbery"],"id":723157026143125504,"text":"Further details now available from @MarquettePD regarding the robbery in the @Marquette_AMU: https://t.co/Ii4njNY77t https://t.co/AMK3nWOrly","keywords":[],"urls":["http://ow.ly/4mVxQq"],"user_verified":false,"class":"Robbery","date":"2016-04-21T02:30:45Z","lang":"en","retweets":0,"city":"Chicago"},{"tags":["robbery"],"id":723151805199183873,"text":"@PainesvilleOhio Please give us an update when you can about the armed robbery","keywords":[],"urls":[],"user_verified":false,"class":"Robbery","date":"2016-04-21T02:10:00Z","lang":"en","retweets":0,"city":"Chicago"},{"tags":["robbery"],"id":723151447873851394,"text":"@atorres086 good. You look like an armed robbery suspect.","keywords":[],"urls":[],"user_verified":false,"class":"Robbery","date":"2016-04-21T02:08:35Z","lang":"en","retweets":0,"city":"Chicago"},{"tags":["robbery"],"id":723148857757020160,"text":"I added a video to a @YouTube playlist https://t.co/vO2Bsdaz8g Proze & Dubes Show 12: Robbery https://t.co/zGLqs0fTFd","keywords":[],"urls":["http://youtu.be/GMnZkN49Fpo?a","http://fb.me/7ScXLZJvZ"],"user_verified":false,"class":"Robbery","date":"2016-04-21T01:58:17Z","lang":"en","retweets":0,"city":"Chicago"},{"tags":["robbery"],"id":723146802216636416,"text":"I added a video to a @YouTube playlist https://t.co/vO2Bsdaz8g Proze & Dubes Show 12: Robbery https://t.co/h9SMQAp8OB","keywords":[],"urls":["http://youtu.be/GMnZkN49Fpo?a","http://fb.me/7QZEQAFcW"],"user_verified":false,"class":"Robbery","date":"2016-04-21T01:50:07Z","lang":"en","retweets":0,"city":"Chicago"},{"tags":["mugging "],"id":723146173326843908,"text":"RT @NoviNovak: I started carrying a knife after an attempted mugging a few years ago. Since then, my mugging attempts have been a lot more\u2026","keywords":[],"urls":[],"user_verified":false,"class":"Robbery","date":"2016-04-21T01:47:37Z","lang":"en","retweets":64,"city":"Chicago"},{"tags":["robbery"],"id":723143074893930496,"text":"I added a video to a @YouTube playlist https://t.co/vO2Bsdaz8g Proze & Dubes Show 12: Robbery","keywords":[],"urls":["http://youtu.be/GMnZkN49Fpo?a"],"user_verified":false,"class":"Robbery","date":"2016-04-21T01:35:19Z","lang":"en","retweets":0,"city":"Chicago"},{"tags":["robbery"],"id":723138212122771456,"text":"Rockford Police investigating armed robbery to Chase Bank https://t.co/Q2Uzl5Zdeo","keywords":[],"urls":["http://ift.tt/210kIOw"],"user_verified":false,"class":"Robbery","date":"2016-04-21T01:15:59Z","lang":"en","retweets":0,"city":"Chicago"},{"tags":["robbery"],"id":723131326417657856,"text":"RT @ABC7Chicago: Lansing police release photos of armed robbery suspect: https://t.co/h6myDLTvdW https://t.co/trGmM0IJZY","keywords":[],"urls":["http://abc7.ws/1SwKdXo"],"user_verified":false,"class":"Robbery","date":"2016-04-21T12:48:38Z","lang":"en","retweets":15,"city":"Chicago"},{"tags":["robbery"],"id":723129804757852162,"text":"The whole world should be charged with robbery then. I don't know anyone who doesn't do this 💀😂 https://t.co/kv9PPbEHSR","keywords":[],"urls":["https://twitter.com/fox5dc/status/722938311870849024"],"user_verified":false,"class":"Robbery","date":"2016-04-21T12:42:35Z","lang":"en","retweets":1,"city":"Chicago"},{"tags":["mugging "],"id":723128492704030720,"text":"Jamari mean mugging .. Too early for that baby boy lmao","keywords":[],"urls":[],"user_verified":false,"class":"Robbery","date":"2016-04-21T12:37:22Z","lang":"en","retweets":0,"city":"Chicago"},{"tags":["shoplifting","shoplifting"],"id":723118537443823616,"text":"MMA Fighter defends clerk during Albuquerque shoplifting incident https://t.co/Ny5sInykom","keywords":[],"urls":["http://ift.tt/2108mpE"],"user_verified":false,"class":"Robbery","date":"2016-04-21T11:57:48Z","lang":"en","retweets":0,"city":"Chicago"},{"tags":["robbery"],"id":723112931672625152,"text":"Felony robbery charge too.... Smh https://t.co/a5HfZ8zuum","keywords":[],"urls":["https://twitter.com/fox5dc/status/722938311870849024"],"user_verified":false,"class":"Robbery","date":"2016-04-21T11:35:32Z","lang":"en","retweets":0,"city":"Chicago"},{"tags":["robbery"],"id":723109254442434560,"text":"Tuesday Halton Police arrested a 51 year old Brantford man responsible for an attempted robbery. February 8th,... https://t.co/TmcLcGAZYr","keywords":[],"urls":["http://fb.me/2lmmg5hba"],"user_verified":false,"class":"Robbery","date":"2016-04-21T11:20:55Z","lang":"en","retweets":0,"city":"Chicago"},{"tags":["robbery"],"id":723108904834613249,"text":"#RockfordScanner Home Invasion In Rockford https://t.co/35yVG6YOmR #robbery #rockford #2016ataround1000pm","keywords":["RockfordScanner","robbery","rockford","2016ataround1000pm"],"urls":["http://goo.gl/fb/BBTWyQ"],"user_verified":false,"class":"Robbery","date":"2016-04-21T11:19:32Z","lang":"en","retweets":0,"city":"Chicago"},{"tags":["robbery"],"id":723095687261380608,"text":"Rockford Police investigating armed robbery to Chase Bank - WREX https://t.co/yEj7y62lZi","keywords":[],"urls":["http://www.snsanalytics.com/Aa4Py1"],"user_verified":false,"class":"Robbery","date":"2016-04-21T10:27:00Z","lang":"en","retweets":0,"city":"Chicago"},{"tags":["robbery"],"id":723090779036614656,"text":"Armed Bank Robbery Suspect on the Run, Rockford Police Investigating https://t.co/exKNmfta3i","keywords":[],"urls":["http://ift.tt/1YIpI8L"],"user_verified":false,"class":"Robbery","date":"2016-04-21T10:07:30Z","lang":"en","retweets":0,"city":"Chicago"},{"tags":["robbery"],"id":723090774397726721,"text":"Rockford Police Investigating Bank Robbery https://t.co/u6fxB1UMRB","keywords":[],"urls":["http://ift.tt/1YIpFJZ"],"user_verified":false,"class":"Robbery","date":"2016-04-21T10:07:29Z","lang":"en","retweets":0,"city":"Chicago"},{"tags":["robbery"],"id":723090215116509184,"text":"RT @CSTbreaking: Police released photos of the suspect in an armed robbery at the Kedzie Pink Line station. https://t.co/DplMbHkCOo https:/\u2026","keywords":[],"urls":["http://wp.me/p7fJAs-Q0X"],"user_verified":false,"class":"Robbery","date":"2016-04-21T10:05:16Z","lang":"en","retweets":2,"city":"Chicago"},{"tags":["robbery"],"id":723064666122031104,"text":"RT @ABC7Chicago: Lansing police release photos of armed robbery suspect: https://t.co/h6myDLTvdW https://t.co/trGmM0IJZY","keywords":[],"urls":["http://abc7.ws/1SwKdXo"],"user_verified":false,"class":"Robbery","date":"2016-04-21T08:23:44Z","lang":"en","retweets":15,"city":"Chicago"}]